{"sections":[],"abstract":[{"type":"text","text":"The base protocol for all TUIkit views."}],"relationshipsSections":[{"kind":"relationships","identifiers":["doc:\/\/TUIkit\/documentation\/TUIkit\/Alert","doc:\/\/TUIkit\/documentation\/TUIkit\/AlertPresentationModifier","doc:\/\/TUIkit\/documentation\/TUIkit\/AnyView","doc:\/\/TUIkit\/documentation\/TUIkit\/BadgeModifier","doc:\/\/TUIkit\/documentation\/TUIkit\/Button","doc:\/\/TUIkit\/documentation\/TUIkit\/ButtonRow","doc:\/\/TUIkit\/documentation\/TUIkit\/Card","doc:\/\/TUIkit\/documentation\/TUIkit\/ConditionalView","doc:\/\/TUIkit\/documentation\/TUIkit\/Dialog","doc:\/\/TUIkit\/documentation\/TUIkit\/DimmedModifier","doc:\/\/TUIkit\/documentation\/TUIkit\/Divider","doc:\/\/TUIkit\/documentation\/TUIkit\/EmptyView","doc:\/\/TUIkit\/documentation\/TUIkit\/EquatableView","doc:\/\/TUIkit\/documentation\/TUIkit\/FlexibleFrameView","doc:\/\/TUIkit\/documentation\/TUIkit\/ForEach","doc:\/\/TUIkit\/documentation\/TUIkit\/HStack","doc:\/\/TUIkit\/documentation\/TUIkit\/KeyPressModifier","doc:\/\/TUIkit\/documentation\/TUIkit\/LazyHStack","doc:\/\/TUIkit\/documentation\/TUIkit\/LazyVStack","doc:\/\/TUIkit\/documentation\/TUIkit\/List","doc:\/\/TUIkit\/documentation\/TUIkit\/ListRowSeparatorModifier","doc:\/\/TUIkit\/documentation\/TUIkit\/Menu","doc:\/\/TUIkit\/documentation\/TUIkit\/ModalPresentationModifier","doc:\/\/TUIkit\/documentation\/TUIkit\/ModifiedView","doc:\/\/TUIkit\/documentation\/TUIkit\/NavigationSplitView","doc:\/\/TUIkit\/documentation\/TUIkit\/Swift\/Never","doc:\/\/TUIkit\/documentation\/TUIkit\/Swift\/Optional","doc:\/\/TUIkit\/documentation\/TUIkit\/OverlayModifier","doc:\/\/TUIkit\/documentation\/TUIkit\/Panel","doc:\/\/TUIkit\/documentation\/TUIkit\/ProgressView","doc:\/\/TUIkit\/documentation\/TUIkit\/RadioButtonGroup","doc:\/\/TUIkit\/documentation\/TUIkit\/Section","doc:\/\/TUIkit\/documentation\/TUIkit\/SecureField","doc:\/\/TUIkit\/documentation\/TUIkit\/SelectionDisabledModifier","doc:\/\/TUIkit\/documentation\/TUIkit\/Slider","doc:\/\/TUIkit\/documentation\/TUIkit\/Spacer","doc:\/\/TUIkit\/documentation\/TUIkit\/Spinner","doc:\/\/TUIkit\/documentation\/TUIkit\/StatusBar","doc:\/\/TUIkit\/documentation\/TUIkit\/Stepper","doc:\/\/TUIkit\/documentation\/TUIkit\/Table","doc:\/\/TUIkit\/documentation\/TUIkit\/Text","doc:\/\/TUIkit\/documentation\/TUIkit\/TextField","doc:\/\/TUIkit\/documentation\/TUIkit\/Toggle","doc:\/\/TUIkit\/documentation\/TUIkit\/TupleView","doc:\/\/TUIkit\/documentation\/TUIkit\/VStack","doc:\/\/TUIkit\/documentation\/TUIkit\/ViewArray","doc:\/\/TUIkit\/documentation\/TUIkit\/ZStack"],"title":"Conforming Types","type":"conformingTypes"}],"topicSections":[{"identifiers":["doc:\/\/TUIkit\/documentation\/TUIkit\/View\/Body-swift.associatedtype"],"title":"Associated Types","generated":true,"anchor":"Associated-Types"},{"identifiers":["doc:\/\/TUIkit\/documentation\/TUIkit\/View\/body-swift.property"],"title":"Instance Properties","generated":true,"anchor":"Instance-Properties"},{"identifiers":["doc:\/\/TUIkit\/documentation\/TUIkit\/View\/alert(_:isPresented:actions:borderStyle:borderColor:titleColor:)","doc:\/\/TUIkit\/documentation\/TUIkit\/View\/alert(_:isPresented:actions:message:borderStyle:borderColor:titleColor:)","doc:\/\/TUIkit\/documentation\/TUIkit\/View\/appHeader(content:)","doc:\/\/TUIkit\/documentation\/TUIkit\/View\/appearance(_:)","doc:\/\/TUIkit\/documentation\/TUIkit\/View\/asAnyView()","doc:\/\/TUIkit\/documentation\/TUIkit\/View\/background(_:)","doc:\/\/TUIkit\/documentation\/TUIkit\/View\/badge(_:)-6or8s","doc:\/\/TUIkit\/documentation\/TUIkit\/View\/badge(_:)-9qomv","doc:\/\/TUIkit\/documentation\/TUIkit\/View\/border(_:color:)","doc:\/\/TUIkit\/documentation\/TUIkit\/View\/dimmed()","doc:\/\/TUIkit\/documentation\/TUIkit\/View\/environment(_:_:)","doc:\/\/TUIkit\/documentation\/TUIkit\/View\/equatable()","doc:\/\/TUIkit\/documentation\/TUIkit\/View\/focusSection(_:)","doc:\/\/TUIkit\/documentation\/TUIkit\/View\/foregroundStyle(_:)","doc:\/\/TUIkit\/documentation\/TUIkit\/View\/frame(minWidth:idealWidth:maxWidth:minHeight:idealHeight:maxHeight:alignment:)","doc:\/\/TUIkit\/documentation\/TUIkit\/View\/frame(width:height:alignment:)","doc:\/\/TUIkit\/documentation\/TUIkit\/View\/listRowSeparator(_:edges:)","doc:\/\/TUIkit\/documentation\/TUIkit\/View\/listStyle(_:)","doc:\/\/TUIkit\/documentation\/TUIkit\/View\/modal(content:)","doc:\/\/TUIkit\/documentation\/TUIkit\/View\/modal(isPresented:content:)","doc:\/\/TUIkit\/documentation\/TUIkit\/View\/modifier(_:)","doc:\/\/TUIkit\/documentation\/TUIkit\/View\/navigationSplitViewColumnWidth(_:)","doc:\/\/TUIkit\/documentation\/TUIkit\/View\/navigationSplitViewColumnWidth(min:ideal:max:)","doc:\/\/TUIkit\/documentation\/TUIkit\/View\/navigationSplitViewStyle(_:)","doc:\/\/TUIkit\/documentation\/TUIkit\/View\/navigationTitle(_:)","doc:\/\/TUIkit\/documentation\/TUIkit\/View\/notificationHost(width:)","doc:\/\/TUIkit\/documentation\/TUIkit\/View\/onAppear(perform:)","doc:\/\/TUIkit\/documentation\/TUIkit\/View\/onDisappear(perform:)","doc:\/\/TUIkit\/documentation\/TUIkit\/View\/onKeyPress(_:)","doc:\/\/TUIkit\/documentation\/TUIkit\/View\/onKeyPress(_:action:)","doc:\/\/TUIkit\/documentation\/TUIkit\/View\/onKeyPress(keys:handler:)","doc:\/\/TUIkit\/documentation\/TUIkit\/View\/onPreferenceChange(_:perform:)","doc:\/\/TUIkit\/documentation\/TUIkit\/View\/overlay(alignment:content:)","doc:\/\/TUIkit\/documentation\/TUIkit\/View\/padding(_:)-6paoy","doc:\/\/TUIkit\/documentation\/TUIkit\/View\/padding(_:)-9pnxu","doc:\/\/TUIkit\/documentation\/TUIkit\/View\/padding(_:_:)","doc:\/\/TUIkit\/documentation\/TUIkit\/View\/palette(_:)","doc:\/\/TUIkit\/documentation\/TUIkit\/View\/preference(key:value:)","doc:\/\/TUIkit\/documentation\/TUIkit\/View\/selectionDisabled(_:)","doc:\/\/TUIkit\/documentation\/TUIkit\/View\/statusBarItems(_:)-1sycu","doc:\/\/TUIkit\/documentation\/TUIkit\/View\/statusBarItems(_:)-9hfph","doc:\/\/TUIkit\/documentation\/TUIkit\/View\/statusBarItems(_:_:)","doc:\/\/TUIkit\/documentation\/TUIkit\/View\/statusBarItems(context:_:)","doc:\/\/TUIkit\/documentation\/TUIkit\/View\/statusBarItems(context:items:)","doc:\/\/TUIkit\/documentation\/TUIkit\/View\/statusBarSystemItems(theme:appearance:)","doc:\/\/TUIkit\/documentation\/TUIkit\/View\/task(priority:_:)","doc:\/\/TUIkit\/documentation\/TUIkit\/View\/textCursor(_:)","doc:\/\/TUIkit\/documentation\/TUIkit\/View\/textCursor(_:animation:speed:)","doc:\/\/TUIkit\/documentation\/TUIkit\/View\/toggleStyle(_:)"],"title":"Instance Methods","generated":true,"anchor":"Instance-Methods"}],"variants":[{"traits":[{"interfaceLanguage":"swift"}],"paths":["\/documentation\/tuikit\/view"]}],"identifier":{"interfaceLanguage":"swift","url":"doc:\/\/TUIkit\/documentation\/TUIkit\/View"},"metadata":{"fragments":[{"text":"protocol","kind":"keyword"},{"text":" ","kind":"text"},{"text":"View","kind":"identifier"}],"externalID":"s:6TUIkit4ViewP","navigatorTitle":[{"text":"View","kind":"identifier"}],"roleHeading":"Protocol","role":"symbol","title":"View","modules":[{"name":"TUIkit"}],"symbolKind":"protocol"},"schemaVersion":{"minor":3,"major":0,"patch":0},"hierarchy":{"paths":[["doc:\/\/TUIkit\/documentation\/TUIkit"]]},"seeAlsoSections":[{"identifiers":["doc:\/\/TUIkit\/documentation\/TUIkit\/Text","doc:\/\/TUIkit\/documentation\/TUIkit\/EmptyView","doc:\/\/TUIkit\/documentation\/TUIkit\/AnyView","doc:\/\/TUIkit\/documentation\/TUIkit\/Spinner","doc:\/\/TUIkit\/documentation\/TUIkit\/Divider"],"title":"Views","generated":true,"anchor":"Views"}],"kind":"symbol","primaryContentSections":[{"kind":"declarations","declarations":[{"platforms":["macOS"],"languages":["swift"],"tokens":[{"text":"@","kind":"attribute"},{"text":"MainActor","kind":"attribute","preciseIdentifier":"s:ScM"},{"text":" ","kind":"text"},{"text":"protocol","kind":"keyword"},{"text":" ","kind":"text"},{"text":"View","kind":"identifier"}]}]},{"kind":"content","content":[{"type":"heading","level":2,"text":"Overview","anchor":"overview"},{"type":"paragraph","inlineContent":[{"code":"View","type":"codeVoice"},{"text":" is the central protocol in TUIkit and works similarly to ","type":"text"},{"code":"View","type":"codeVoice"},{"text":" in SwiftUI.","type":"text"},{"text":" ","type":"text"},{"text":"It defines how components declare their structure and content.","type":"text"}]},{"type":"paragraph","inlineContent":[{"type":"text","text":"Every View defines a "},{"type":"codeVoice","code":"body"},{"type":"text","text":" composed of other Views."},{"type":"text","text":" "},{"type":"text","text":"This enables a hierarchical, declarative UI description."}]},{"type":"heading","level":2,"text":"Dual Rendering System","anchor":"Dual-Rendering-System"},{"type":"paragraph","inlineContent":[{"text":"TUIkit uses two rendering paths:","type":"text"}]},{"type":"unorderedList","items":[{"content":[{"type":"paragraph","inlineContent":[{"inlineContent":[{"type":"text","text":"Composite views"}],"type":"strong"},{"type":"text","text":" implement "},{"type":"codeVoice","code":"body"},{"type":"text","text":" to compose other views."},{"type":"text","text":" "},{"type":"text","text":"The rendering system recurses into "},{"type":"codeVoice","code":"body"},{"type":"text","text":" to resolve the tree."}]}]},{"content":[{"type":"paragraph","inlineContent":[{"inlineContent":[{"text":"Primitive views","type":"text"}],"type":"strong"},{"type":"text","text":" additionally conform to "},{"type":"codeVoice","code":"Renderable"},{"type":"text","text":" and"},{"type":"text","text":" "},{"type":"text","text":"produce a "},{"type":"reference","identifier":"doc:\/\/TUIkit\/documentation\/TUIkit\/FrameBuffer","isActive":true},{"type":"text","text":" directly. They set "},{"type":"codeVoice","code":"body: Never"},{"type":"text","text":" "},{"type":"text","text":"(which "},{"type":"codeVoice","code":"fatalError"},{"type":"text","text":"s if called) because their "},{"type":"codeVoice","code":"body"},{"type":"text","text":" is never used."}]}]}]},{"type":"paragraph","inlineContent":[{"type":"text","text":"The free function "},{"type":"codeVoice","code":"renderToBuffer(_:context:)"},{"type":"text","text":" checks "},{"type":"codeVoice","code":"Renderable"},{"type":"text","text":" "},{"type":"text","text":"first, then falls back to "},{"type":"codeVoice","code":"body"},{"type":"text","text":". See "},{"type":"codeVoice","code":"Renderable"},{"type":"text","text":" for details."}]},{"type":"heading","level":2,"text":"Creating a composite view","anchor":"Creating-a-composite-view"},{"type":"codeListing","syntax":"swift","code":["struct MyView: View {","    var body: some View {","        Text(\"Hello, TUIkit!\")","    }","}"]},{"type":"heading","level":2,"text":"Creating a primitive view","anchor":"Creating-a-primitive-view"},{"type":"codeListing","syntax":"swift","code":["struct MyPrimitive: View {","    var body: Never { fatalError() }","}","","extension MyPrimitive: Renderable {","    func renderToBuffer(context: RenderContext) -> FrameBuffer {","        FrameBuffer(text: \"output\")","    }","}"]},{"type":"heading","level":2,"text":"Thread Safety","anchor":"Thread-Safety"},{"type":"paragraph","inlineContent":[{"text":"Like SwiftUI, all view operations are confined to the main actor.","type":"text"},{"text":" ","type":"text"},{"text":"This ensures thread-safe access to state, environment, and rendering.","type":"text"}]}]}],"references":{"doc://TUIkit/documentation/TUIkit/View/textCursor(_:animation:speed:)":{"kind":"symbol","title":"textCursor(_:animation:speed:)","url":"\/documentation\/tuikit\/view\/textcursor(_:animation:speed:)","type":"topic","fragments":[{"kind":"keyword","text":"func"},{"kind":"text","text":" "},{"kind":"identifier","text":"textCursor"},{"kind":"text","text":"("},{"preciseIdentifier":"s:6TUIkit15TextCursorStyleV","kind":"typeIdentifier","text":"TextCursorStyle"},{"kind":"text","text":"."},{"preciseIdentifier":"s:6TUIkit15TextCursorStyleV5ShapeO","kind":"typeIdentifier","text":"Shape"},{"kind":"text","text":", "},{"kind":"externalParam","text":"animation"},{"kind":"text","text":": "},{"preciseIdentifier":"s:6TUIkit15TextCursorStyleV","kind":"typeIdentifier","text":"TextCursorStyle"},{"kind":"text","text":"."},{"preciseIdentifier":"s:6TUIkit15TextCursorStyleV9AnimationO","kind":"typeIdentifier","text":"Animation"},{"kind":"text","text":", "},{"kind":"externalParam","text":"speed"},{"kind":"text","text":": "},{"preciseIdentifier":"s:6TUIkit15TextCursorStyleV","kind":"typeIdentifier","text":"TextCursorStyle"},{"kind":"text","text":"."},{"preciseIdentifier":"s:6TUIkit15TextCursorStyleV5SpeedO","kind":"typeIdentifier","text":"Speed"},{"kind":"text","text":") -> "},{"kind":"keyword","text":"some"},{"kind":"text","text":" "},{"preciseIdentifier":"s:6TUIkit4ViewP","kind":"typeIdentifier","text":"View"}],"role":"symbol","abstract":[{"type":"text","text":"Sets the text cursor style with separate shape, animation, and speed parameters."}],"identifier":"doc:\/\/TUIkit\/documentation\/TUIkit\/View\/textCursor(_:animation:speed:)"},"doc://TUIkit/documentation/TUIkit/View/foregroundStyle(_:)":{"kind":"symbol","role":"symbol","abstract":[{"text":"Sets the foreground style for this view and its children.","type":"text"}],"title":"foregroundStyle(_:)","fragments":[{"text":"func","kind":"keyword"},{"text":" ","kind":"text"},{"text":"foregroundStyle","kind":"identifier"},{"text":"(","kind":"text"},{"text":"Color","kind":"typeIdentifier","preciseIdentifier":"s:6TUIkit5ColorV"},{"text":"?) -> ","kind":"text"},{"text":"some","kind":"keyword"},{"text":" ","kind":"text"},{"text":"View","kind":"typeIdentifier","preciseIdentifier":"s:6TUIkit4ViewP"}],"identifier":"doc:\/\/TUIkit\/documentation\/TUIkit\/View\/foregroundStyle(_:)","url":"\/documentation\/tuikit\/view\/foregroundstyle(_:)","type":"topic"},"doc://TUIkit/documentation/TUIkit/View/palette(_:)":{"kind":"symbol","abstract":[{"text":"Sets the color palette for this view and its descendants.","type":"text"}],"role":"symbol","type":"topic","title":"palette(_:)","url":"\/documentation\/tuikit\/view\/palette(_:)","identifier":"doc:\/\/TUIkit\/documentation\/TUIkit\/View\/palette(_:)","fragments":[{"kind":"keyword","text":"func"},{"kind":"text","text":" "},{"kind":"identifier","text":"palette"},{"kind":"text","text":"(any "},{"preciseIdentifier":"s:6TUIkit7PaletteP","kind":"typeIdentifier","text":"Palette"},{"kind":"text","text":") -> "},{"kind":"keyword","text":"some"},{"kind":"text","text":" "},{"preciseIdentifier":"s:6TUIkit4ViewP","kind":"typeIdentifier","text":"View"}]},"doc://TUIkit/documentation/TUIkit/ZStack":{"navigatorTitle":[{"text":"ZStack","kind":"identifier"}],"title":"ZStack","kind":"symbol","role":"symbol","fragments":[{"text":"struct","kind":"keyword"},{"text":" ","kind":"text"},{"text":"ZStack","kind":"identifier"}],"abstract":[{"type":"text","text":"A view that stacks its children on top of each other (z-axis)."}],"url":"\/documentation\/tuikit\/zstack","identifier":"doc:\/\/TUIkit\/documentation\/TUIkit\/ZStack","type":"topic"},"doc://TUIkit/documentation/TUIkit/Section":{"role":"symbol","fragments":[{"text":"struct","kind":"keyword"},{"text":" ","kind":"text"},{"text":"Section","kind":"identifier"}],"identifier":"doc:\/\/TUIkit\/documentation\/TUIkit\/Section","title":"Section","type":"topic","kind":"symbol","url":"\/documentation\/tuikit\/section","navigatorTitle":[{"text":"Section","kind":"identifier"}],"abstract":[{"text":"A container view that groups content with optional header and footer.","type":"text"}]},"doc://TUIkit/documentation/TUIkit/Button":{"url":"\/documentation\/tuikit\/button","kind":"symbol","type":"topic","navigatorTitle":[{"kind":"identifier","text":"Button"}],"role":"symbol","identifier":"doc:\/\/TUIkit\/documentation\/TUIkit\/Button","abstract":[{"type":"text","text":"An interactive button that triggers an action when pressed."}],"title":"Button","fragments":[{"kind":"keyword","text":"struct"},{"kind":"text","text":" "},{"kind":"identifier","text":"Button"}]},"tuikit-logo.png":{"identifier":"tuikit-logo.png","variants":[{"url":"\/images\/TUIkit\/tuikit-logo.png","traits":["1x","light"]}],"type":"image","alt":"TUIkit Logo"},"doc://TUIkit/documentation/TUIkit/View/statusBarItems(_:_:)":{"fragments":[{"kind":"keyword","text":"func"},{"kind":"text","text":" "},{"kind":"identifier","text":"statusBarItems"},{"kind":"text","text":"("},{"preciseIdentifier":"s:6TUIkit24StatusBarItemCompositionO","kind":"typeIdentifier","text":"StatusBarItemComposition"},{"kind":"text","text":", () -> [any "},{"preciseIdentifier":"s:6TUIkit21StatusBarItemProtocolP","kind":"typeIdentifier","text":"StatusBarItemProtocol"},{"kind":"text","text":"]) -> "},{"kind":"keyword","text":"some"},{"kind":"text","text":" "},{"preciseIdentifier":"s:6TUIkit4ViewP","kind":"typeIdentifier","text":"View"}],"identifier":"doc:\/\/TUIkit\/documentation\/TUIkit\/View\/statusBarItems(_:_:)","abstract":[{"text":"Declares status bar items with a specific composition strategy.","type":"text"}],"kind":"symbol","url":"\/documentation\/tuikit\/view\/statusbaritems(_:_:)","title":"statusBarItems(_:_:)","role":"symbol","type":"topic"},"doc://TUIkit/documentation/TUIkit/List":{"abstract":[{"type":"text","text":"A scrollable list with keyboard navigation and single selection."}],"kind":"symbol","identifier":"doc:\/\/TUIkit\/documentation\/TUIkit\/List","role":"symbol","title":"List","url":"\/documentation\/tuikit\/list","navigatorTitle":[{"text":"List","kind":"identifier"}],"type":"topic","fragments":[{"text":"struct","kind":"keyword"},{"text":" ","kind":"text"},{"text":"List","kind":"identifier"}]},"doc://TUIkit/documentation/TUIkit/ButtonRow":{"title":"ButtonRow","fragments":[{"kind":"keyword","text":"struct"},{"kind":"text","text":" "},{"kind":"identifier","text":"ButtonRow"}],"navigatorTitle":[{"kind":"identifier","text":"ButtonRow"}],"identifier":"doc:\/\/TUIkit\/documentation\/TUIkit\/ButtonRow","url":"\/documentation\/tuikit\/buttonrow","kind":"symbol","abstract":[{"text":"A horizontal row of buttons.","type":"text"}],"role":"symbol","type":"topic"},"doc://TUIkit/documentation/TUIkit/ModifiedView":{"identifier":"doc:\/\/TUIkit\/documentation\/TUIkit\/ModifiedView","fragments":[{"kind":"keyword","text":"struct"},{"kind":"text","text":" "},{"kind":"identifier","text":"ModifiedView"}],"url":"\/documentation\/tuikit\/modifiedview","kind":"symbol","abstract":[{"text":"A view that wraps another view with a modifier.","type":"text"}],"title":"ModifiedView","type":"topic","role":"symbol","navigatorTitle":[{"kind":"identifier","text":"ModifiedView"}]},"doc://TUIkit/documentation/TUIkit/BadgeModifier":{"kind":"symbol","title":"BadgeModifier","fragments":[{"text":"struct","kind":"keyword"},{"text":" ","kind":"text"},{"text":"BadgeModifier","kind":"identifier"}],"url":"\/documentation\/tuikit\/badgemodifier","identifier":"doc:\/\/TUIkit\/documentation\/TUIkit\/BadgeModifier","abstract":[{"text":"A modifier that displays a decorative badge on a view.","type":"text"}],"role":"symbol","type":"topic","navigatorTitle":[{"text":"BadgeModifier","kind":"identifier"}]},"doc://TUIkit/documentation/TUIkit/View/listStyle(_:)":{"role":"symbol","identifier":"doc:\/\/TUIkit\/documentation\/TUIkit\/View\/listStyle(_:)","url":"\/documentation\/tuikit\/view\/liststyle(_:)","type":"topic","fragments":[{"kind":"keyword","text":"func"},{"kind":"text","text":" "},{"kind":"identifier","text":"listStyle"},{"kind":"text","text":"(any "},{"kind":"typeIdentifier","text":"ListStyle","preciseIdentifier":"s:6TUIkit9ListStyleP"},{"kind":"text","text":") -> "},{"kind":"keyword","text":"some"},{"kind":"text","text":" "},{"kind":"typeIdentifier","text":"View","preciseIdentifier":"s:6TUIkit4ViewP"}],"kind":"symbol","title":"listStyle(_:)","abstract":[{"text":"Sets the list style for List views in this view and its descendants.","type":"text"}]},"doc://TUIkit/documentation/TUIkit/LazyHStack":{"url":"\/documentation\/tuikit\/lazyhstack","role":"symbol","fragments":[{"text":"struct","kind":"keyword"},{"kind":"text","text":" "},{"kind":"identifier","text":"LazyHStack"}],"title":"LazyHStack","identifier":"doc:\/\/TUIkit\/documentation\/TUIkit\/LazyHStack","kind":"symbol","navigatorTitle":[{"kind":"identifier","text":"LazyHStack"}],"type":"topic","abstract":[{"type":"text","text":"A view that arranges its children in a line that grows horizontally,"},{"type":"text","text":" "},{"type":"text","text":"creating items only as needed."}]},"doc://TUIkit/documentation/TUIkit/Menu":{"type":"topic","abstract":[{"text":"A vertical menu displaying a list of selectable items.","type":"text"}],"identifier":"doc:\/\/TUIkit\/documentation\/TUIkit\/Menu","title":"Menu","role":"symbol","fragments":[{"kind":"keyword","text":"struct"},{"kind":"text","text":" "},{"kind":"identifier","text":"Menu"}],"navigatorTitle":[{"kind":"identifier","text":"Menu"}],"kind":"symbol","url":"\/documentation\/tuikit\/menu"},"doc://TUIkit/documentation/TUIkit/Spacer":{"title":"Spacer","abstract":[{"text":"A flexible spacer that fills available space.","type":"text"}],"url":"\/documentation\/tuikit\/spacer","type":"topic","role":"symbol","navigatorTitle":[{"text":"Spacer","kind":"identifier"}],"kind":"symbol","identifier":"doc:\/\/TUIkit\/documentation\/TUIkit\/Spacer","fragments":[{"text":"struct","kind":"keyword"},{"text":" ","kind":"text"},{"text":"Spacer","kind":"identifier"}]},"doc://TUIkit/documentation/TUIkit":{"type":"topic","url":"\/documentation\/tuikit","title":"TUIkit","identifier":"doc:\/\/TUIkit\/documentation\/TUIkit","role":"collection","abstract":[{"text":"A declarative, SwiftUI-like framework for building Terminal User Interfaces in Swift.","type":"text"}],"images":[{"identifier":"tuikit-logo.png","type":"icon"},{"identifier":"tuikit-logo.png","type":"card"}],"kind":"symbol"},"doc://TUIkit/documentation/TUIkit/TextField":{"url":"\/documentation\/tuikit\/textfield","navigatorTitle":[{"kind":"identifier","text":"TextField"}],"fragments":[{"kind":"keyword","text":"struct"},{"kind":"text","text":" "},{"kind":"identifier","text":"TextField"}],"kind":"symbol","identifier":"doc:\/\/TUIkit\/documentation\/TUIkit\/TextField","role":"symbol","type":"topic","title":"TextField","abstract":[{"text":"A control that displays an editable text interface.","type":"text"}]},"doc://TUIkit/documentation/TUIkit/Dialog":{"role":"symbol","fragments":[{"text":"struct","kind":"keyword"},{"text":" ","kind":"text"},{"text":"Dialog","kind":"identifier"}],"identifier":"doc:\/\/TUIkit\/documentation\/TUIkit\/Dialog","url":"\/documentation\/tuikit\/dialog","title":"Dialog","type":"topic","kind":"symbol","navigatorTitle":[{"text":"Dialog","kind":"identifier"}],"abstract":[{"type":"text","text":"A modal dialog view with a title, customizable content, and optional footer."}]},"doc://TUIkit/documentation/TUIkit/View/modifier(_:)":{"kind":"symbol","url":"\/documentation\/tuikit\/view\/modifier(_:)","role":"symbol","identifier":"doc:\/\/TUIkit\/documentation\/TUIkit\/View\/modifier(_:)","abstract":[{"text":"Applies a modifier to this view.","type":"text"}],"type":"topic","title":"modifier(_:)","fragments":[{"text":"func","kind":"keyword"},{"text":" ","kind":"text"},{"text":"modifier","kind":"identifier"},{"text":"<","kind":"text"},{"text":"M","kind":"genericParameter"},{"text":">(","kind":"text"},{"text":"M","kind":"typeIdentifier"},{"text":") -> ","kind":"text"},{"text":"ModifiedView","kind":"typeIdentifier","preciseIdentifier":"s:6TUIkit12ModifiedViewV"},{"text":"<","kind":"text"},{"text":"Self","kind":"typeIdentifier"},{"text":", ","kind":"text"},{"text":"M","kind":"typeIdentifier"},{"text":">","kind":"text"}]},"doc://TUIkit/documentation/TUIkit/NavigationSplitView":{"type":"topic","role":"symbol","url":"\/documentation\/tuikit\/navigationsplitview","kind":"symbol","title":"NavigationSplitView","fragments":[{"text":"struct","kind":"keyword"},{"text":" ","kind":"text"},{"text":"NavigationSplitView","kind":"identifier"}],"abstract":[{"text":"A view that presents views in two or three columns, where selections in","type":"text"},{"text":" ","type":"text"},{"text":"leading columns control presentations in subsequent columns.","type":"text"}],"navigatorTitle":[{"text":"NavigationSplitView","kind":"identifier"}],"identifier":"doc:\/\/TUIkit\/documentation\/TUIkit\/NavigationSplitView"},"doc://TUIkit/documentation/TUIkit/View/preference(key:value:)":{"title":"preference(key:value:)","identifier":"doc:\/\/TUIkit\/documentation\/TUIkit\/View\/preference(key:value:)","fragments":[{"kind":"keyword","text":"func"},{"kind":"text","text":" "},{"kind":"identifier","text":"preference"},{"kind":"text","text":"<"},{"kind":"genericParameter","text":"K"},{"kind":"text","text":">("},{"kind":"externalParam","text":"key"},{"kind":"text","text":": "},{"kind":"typeIdentifier","text":"K"},{"kind":"text","text":".Type, "},{"kind":"externalParam","text":"value"},{"kind":"text","text":": "},{"kind":"typeIdentifier","text":"K"},{"kind":"text","text":"."},{"kind":"typeIdentifier","preciseIdentifier":"s:6TUIkit13PreferenceKeyP5ValueQa","text":"Value"},{"kind":"text","text":") -> "},{"kind":"keyword","text":"some"},{"kind":"text","text":" "},{"kind":"typeIdentifier","preciseIdentifier":"s:6TUIkit4ViewP","text":"View"}],"role":"symbol","kind":"symbol","url":"\/documentation\/tuikit\/view\/preference(key:value:)","type":"topic","abstract":[{"type":"text","text":"Sets a preference value for this view."}]},"doc://TUIkit/documentation/TUIkit/View/frame(width:height:alignment:)":{"title":"frame(width:height:alignment:)","identifier":"doc:\/\/TUIkit\/documentation\/TUIkit\/View\/frame(width:height:alignment:)","fragments":[{"kind":"keyword","text":"func"},{"kind":"text","text":" "},{"kind":"identifier","text":"frame"},{"kind":"text","text":"("},{"kind":"externalParam","text":"width"},{"kind":"text","text":": "},{"kind":"typeIdentifier","preciseIdentifier":"s:Si","text":"Int"},{"kind":"text","text":"?, "},{"kind":"externalParam","text":"height"},{"kind":"text","text":": "},{"kind":"typeIdentifier","preciseIdentifier":"s:Si","text":"Int"},{"kind":"text","text":"?, "},{"kind":"externalParam","text":"alignment"},{"kind":"text","text":": "},{"kind":"typeIdentifier","preciseIdentifier":"s:6TUIkit9AlignmentV","text":"Alignment"},{"kind":"text","text":") -> "},{"kind":"keyword","text":"some"},{"kind":"text","text":" "},{"kind":"typeIdentifier","preciseIdentifier":"s:6TUIkit4ViewP","text":"View"}],"role":"symbol","kind":"symbol","url":"\/documentation\/tuikit\/view\/frame(width:height:alignment:)","abstract":[{"type":"text","text":"Sets an explicit frame size for this view."}],"type":"topic"},"doc://TUIkit/documentation/TUIkit/Stepper":{"abstract":[{"type":"text","text":"A control that performs increment and decrement actions."}],"navigatorTitle":[{"kind":"identifier","text":"Stepper"}],"type":"topic","kind":"symbol","fragments":[{"kind":"keyword","text":"struct"},{"kind":"text","text":" "},{"kind":"identifier","text":"Stepper"}],"identifier":"doc:\/\/TUIkit\/documentation\/TUIkit\/Stepper","url":"\/documentation\/tuikit\/stepper","title":"Stepper","role":"symbol"},"doc://TUIkit/documentation/TUIkit/View/statusBarSystemItems(theme:appearance:)":{"title":"statusBarSystemItems(theme:appearance:)","identifier":"doc:\/\/TUIkit\/documentation\/TUIkit\/View\/statusBarSystemItems(theme:appearance:)","fragments":[{"kind":"keyword","text":"func"},{"kind":"text","text":" "},{"kind":"identifier","text":"statusBarSystemItems"},{"kind":"text","text":"("},{"kind":"externalParam","text":"theme"},{"kind":"text","text":": "},{"kind":"typeIdentifier","preciseIdentifier":"s:Sb","text":"Bool"},{"kind":"text","text":", "},{"kind":"externalParam","text":"appearance"},{"kind":"text","text":": "},{"kind":"typeIdentifier","preciseIdentifier":"s:Sb","text":"Bool"},{"kind":"text","text":") -> "},{"kind":"keyword","text":"some"},{"kind":"text","text":" "},{"kind":"typeIdentifier","preciseIdentifier":"s:6TUIkit4ViewP","text":"View"}],"role":"symbol","kind":"symbol","url":"\/documentation\/tuikit\/view\/statusbarsystemitems(theme:appearance:)","type":"topic","abstract":[{"type":"text","text":"Configures which system items are shown in the status bar."}]},"doc://TUIkit/documentation/TUIkit/OverlayModifier":{"kind":"symbol","url":"\/documentation\/tuikit\/overlaymodifier","role":"symbol","fragments":[{"kind":"keyword","text":"struct"},{"kind":"text","text":" "},{"kind":"identifier","text":"OverlayModifier"}],"navigatorTitle":[{"kind":"identifier","text":"OverlayModifier"}],"title":"OverlayModifier","identifier":"doc:\/\/TUIkit\/documentation\/TUIkit\/OverlayModifier","abstract":[{"text":"Internal modifier that layers an overlay view on top of the base content.","type":"text"}],"type":"topic"},"doc://TUIkit/documentation/TUIkit/Toggle":{"fragments":[{"text":"struct","kind":"keyword"},{"text":" ","kind":"text"},{"text":"Toggle","kind":"identifier"}],"kind":"symbol","abstract":[{"text":"A control that toggles between on and off states.","type":"text"}],"title":"Toggle","type":"topic","identifier":"doc:\/\/TUIkit\/documentation\/TUIkit\/Toggle","navigatorTitle":[{"text":"Toggle","kind":"identifier"}],"url":"\/documentation\/tuikit\/toggle","role":"symbol"},"doc://TUIkit/documentation/TUIkit/Card":{"identifier":"doc:\/\/TUIkit\/documentation\/TUIkit\/Card","type":"topic","title":"Card","abstract":[{"type":"text","text":"A padded, optionally titled container with background support."}],"kind":"symbol","url":"\/documentation\/tuikit\/card","role":"symbol","fragments":[{"kind":"keyword","text":"struct"},{"kind":"text","text":" "},{"kind":"identifier","text":"Card"}],"navigatorTitle":[{"kind":"identifier","text":"Card"}]},"doc://TUIkit/documentation/TUIkit/View/notificationHost(width:)":{"type":"topic","url":"\/documentation\/tuikit\/view\/notificationhost(width:)","abstract":[{"type":"text","text":"Makes this view the notification rendering host."}],"kind":"symbol","title":"notificationHost(width:)","role":"symbol","fragments":[{"text":"func","kind":"keyword"},{"text":" ","kind":"text"},{"text":"notificationHost","kind":"identifier"},{"text":"(","kind":"text"},{"text":"width","kind":"externalParam"},{"text":": ","kind":"text"},{"text":"Int","preciseIdentifier":"s:Si","kind":"typeIdentifier"},{"text":") -> ","kind":"text"},{"text":"some","kind":"keyword"},{"text":" ","kind":"text"},{"text":"View","preciseIdentifier":"s:6TUIkit4ViewP","kind":"typeIdentifier"}],"identifier":"doc:\/\/TUIkit\/documentation\/TUIkit\/View\/notificationHost(width:)"},"doc://TUIkit/documentation/TUIkit/View/textCursor(_:)":{"title":"textCursor(_:)","kind":"symbol","type":"topic","abstract":[{"type":"text","text":"Sets the text cursor style for text fields within this view."}],"identifier":"doc:\/\/TUIkit\/documentation\/TUIkit\/View\/textCursor(_:)","fragments":[{"text":"func","kind":"keyword"},{"text":" ","kind":"text"},{"text":"textCursor","kind":"identifier"},{"text":"(","kind":"text"},{"text":"TextCursorStyle","kind":"typeIdentifier","preciseIdentifier":"s:6TUIkit15TextCursorStyleV"},{"text":") -> ","kind":"text"},{"text":"some","kind":"keyword"},{"text":" ","kind":"text"},{"text":"View","kind":"typeIdentifier","preciseIdentifier":"s:6TUIkit4ViewP"}],"role":"symbol","url":"\/documentation\/tuikit\/view\/textcursor(_:)"},"doc://TUIkit/documentation/TUIkit/View/focusSection(_:)":{"identifier":"doc:\/\/TUIkit\/documentation\/TUIkit\/View\/focusSection(_:)","role":"symbol","type":"topic","abstract":[{"text":"Declares this view as a focus section.","type":"text"}],"kind":"symbol","fragments":[{"text":"func","kind":"keyword"},{"text":" ","kind":"text"},{"text":"focusSection","kind":"identifier"},{"text":"(","kind":"text"},{"text":"String","kind":"typeIdentifier","preciseIdentifier":"s:SS"},{"text":") -> ","kind":"text"},{"text":"some","kind":"keyword"},{"text":" ","kind":"text"},{"text":"View","kind":"typeIdentifier","preciseIdentifier":"s:6TUIkit4ViewP"}],"title":"focusSection(_:)","url":"\/documentation\/tuikit\/view\/focussection(_:)"},"doc://TUIkit/documentation/TUIkit/View/padding(_:_:)":{"identifier":"doc:\/\/TUIkit\/documentation\/TUIkit\/View\/padding(_:_:)","role":"symbol","fragments":[{"text":"func","kind":"keyword"},{"text":" ","kind":"text"},{"text":"padding","kind":"identifier"},{"text":"(","kind":"text"},{"preciseIdentifier":"s:6TUIkit4EdgeV","text":"Edge","kind":"typeIdentifier"},{"text":", ","kind":"text"},{"preciseIdentifier":"s:Si","text":"Int","kind":"typeIdentifier"},{"text":") -> ","kind":"text"},{"text":"some","kind":"keyword"},{"text":" ","kind":"text"},{"preciseIdentifier":"s:6TUIkit4ViewP","text":"View","kind":"typeIdentifier"}],"abstract":[{"type":"text","text":"Adds padding on specific edges."}],"title":"padding(_:_:)","type":"topic","kind":"symbol","url":"\/documentation\/tuikit\/view\/padding(_:_:)"},"doc://TUIkit/documentation/TUIkit/View/onPreferenceChange(_:perform:)":{"abstract":[{"type":"text","text":"Adds an action to perform when a preference value changes."}],"identifier":"doc:\/\/TUIkit\/documentation\/TUIkit\/View\/onPreferenceChange(_:perform:)","type":"topic","role":"symbol","url":"\/documentation\/tuikit\/view\/onpreferencechange(_:perform:)","fragments":[{"kind":"keyword","text":"func"},{"kind":"text","text":" "},{"kind":"identifier","text":"onPreferenceChange"},{"kind":"text","text":"<"},{"kind":"genericParameter","text":"K"},{"kind":"text","text":">("},{"kind":"typeIdentifier","text":"K"},{"kind":"text","text":".Type, "},{"kind":"externalParam","text":"perform"},{"kind":"text","text":": ("},{"kind":"typeIdentifier","text":"K"},{"kind":"text","text":"."},{"kind":"typeIdentifier","text":"Value","preciseIdentifier":"s:6TUIkit13PreferenceKeyP5ValueQa"},{"kind":"text","text":") -> "},{"kind":"typeIdentifier","text":"Void","preciseIdentifier":"s:s4Voida"},{"kind":"text","text":") -> "},{"kind":"keyword","text":"some"},{"kind":"text","text":" "},{"kind":"typeIdentifier","text":"View","preciseIdentifier":"s:6TUIkit4ViewP"}],"title":"onPreferenceChange(_:perform:)","kind":"symbol"},"doc://TUIkit/documentation/TUIkit/View/equatable()":{"fragments":[{"kind":"keyword","text":"func"},{"kind":"text","text":" "},{"kind":"identifier","text":"equatable"},{"kind":"text","text":"() -> "},{"preciseIdentifier":"s:6TUIkit13EquatableViewV","kind":"typeIdentifier","text":"EquatableView"},{"kind":"text","text":"<"},{"kind":"typeIdentifier","text":"Self"},{"kind":"text","text":">"}],"conformance":{"conformancePrefix":[{"type":"text","text":"Conforms when"}],"constraints":[{"type":"codeVoice","code":"Self"},{"type":"text","text":" conforms to "},{"type":"codeVoice","code":"Equatable"},{"type":"text","text":"."}],"availabilityPrefix":[{"type":"text","text":"Available when"}]},"role":"symbol","identifier":"doc:\/\/TUIkit\/documentation\/TUIkit\/View\/equatable()","abstract":[{"text":"Wraps this view in an ","type":"text"},{"type":"reference","identifier":"doc:\/\/TUIkit\/documentation\/TUIkit\/EquatableView","isActive":true},{"type":"text","text":" for subtree memoization."}],"title":"equatable()","url":"\/documentation\/tuikit\/view\/equatable()","kind":"symbol","type":"topic"},"doc://TUIkit/documentation/TUIkit/View/frame(minWidth:idealWidth:maxWidth:minHeight:idealHeight:maxHeight:alignment:)":{"abstract":[{"type":"text","text":"Sets flexible frame constraints for this view."}],"identifier":"doc:\/\/TUIkit\/documentation\/TUIkit\/View\/frame(minWidth:idealWidth:maxWidth:minHeight:idealHeight:maxHeight:alignment:)","type":"topic","role":"symbol","url":"\/documentation\/tuikit\/view\/frame(minwidth:idealwidth:maxwidth:minheight:idealheight:maxheight:alignment:)","fragments":[{"kind":"keyword","text":"func"},{"kind":"text","text":" "},{"kind":"identifier","text":"frame"},{"kind":"text","text":"("},{"kind":"externalParam","text":"minWidth"},{"kind":"text","text":": "},{"kind":"typeIdentifier","text":"Int","preciseIdentifier":"s:Si"},{"kind":"text","text":"?, "},{"kind":"externalParam","text":"idealWidth"},{"kind":"text","text":": "},{"kind":"typeIdentifier","text":"Int","preciseIdentifier":"s:Si"},{"kind":"text","text":"?, "},{"kind":"externalParam","text":"maxWidth"},{"kind":"text","text":": "},{"kind":"typeIdentifier","text":"FrameDimension","preciseIdentifier":"s:6TUIkit14FrameDimensionO"},{"kind":"text","text":"?, "},{"kind":"externalParam","text":"minHeight"},{"kind":"text","text":": "},{"kind":"typeIdentifier","text":"Int","preciseIdentifier":"s:Si"},{"kind":"text","text":"?, "},{"kind":"externalParam","text":"idealHeight"},{"kind":"text","text":": "},{"kind":"typeIdentifier","text":"Int","preciseIdentifier":"s:Si"},{"kind":"text","text":"?, "},{"kind":"externalParam","text":"maxHeight"},{"kind":"text","text":": "},{"kind":"typeIdentifier","text":"FrameDimension","preciseIdentifier":"s:6TUIkit14FrameDimensionO"},{"kind":"text","text":"?, "},{"kind":"externalParam","text":"alignment"},{"kind":"text","text":": "},{"kind":"typeIdentifier","text":"Alignment","preciseIdentifier":"s:6TUIkit9AlignmentV"},{"kind":"text","text":") -> "},{"kind":"keyword","text":"some"},{"kind":"text","text":" "},{"kind":"typeIdentifier","text":"View","preciseIdentifier":"s:6TUIkit4ViewP"}],"title":"frame(minWidth:idealWidth:maxWidth:minHeight:idealHeight:maxHeight:alignment:)","kind":"symbol"},"doc://TUIkit/documentation/TUIkit/View/alert(_:isPresented:actions:message:borderStyle:borderColor:titleColor:)":{"abstract":[{"type":"text","text":"Presents an alert when a binding to a Boolean value is true."}],"identifier":"doc:\/\/TUIkit\/documentation\/TUIkit\/View\/alert(_:isPresented:actions:message:borderStyle:borderColor:titleColor:)","type":"topic","role":"symbol","url":"\/documentation\/tuikit\/view\/alert(_:ispresented:actions:message:borderstyle:bordercolor:titlecolor:)","fragments":[{"kind":"keyword","text":"func"},{"kind":"text","text":" "},{"kind":"identifier","text":"alert"},{"kind":"text","text":"<"},{"kind":"genericParameter","text":"Actions"},{"kind":"text","text":", "},{"kind":"genericParameter","text":"Message"},{"kind":"text","text":">("},{"kind":"typeIdentifier","text":"String","preciseIdentifier":"s:SS"},{"kind":"text","text":", "},{"kind":"externalParam","text":"isPresented"},{"kind":"text","text":": "},{"kind":"typeIdentifier","text":"Binding","preciseIdentifier":"s:6TUIkit7BindingV"},{"kind":"text","text":"<"},{"kind":"typeIdentifier","text":"Bool","preciseIdentifier":"s:Sb"},{"kind":"text","text":">, "},{"kind":"externalParam","text":"actions"},{"kind":"text","text":": () -> "},{"kind":"typeIdentifier","text":"Actions"},{"kind":"text","text":", "},{"kind":"externalParam","text":"message"},{"kind":"text","text":": () -> "},{"kind":"typeIdentifier","text":"Message"},{"kind":"text","text":", "},{"kind":"externalParam","text":"borderStyle"},{"kind":"text","text":": "},{"kind":"typeIdentifier","text":"BorderStyle","preciseIdentifier":"s:6TUIkit11BorderStyleV"},{"kind":"text","text":"?, "},{"kind":"externalParam","text":"borderColor"},{"kind":"text","text":": "},{"kind":"typeIdentifier","text":"Color","preciseIdentifier":"s:6TUIkit5ColorV"},{"kind":"text","text":"?, "},{"kind":"externalParam","text":"titleColor"},{"kind":"text","text":": "},{"kind":"typeIdentifier","text":"Color","preciseIdentifier":"s:6TUIkit5ColorV"},{"kind":"text","text":"?) -> "},{"kind":"keyword","text":"some"},{"kind":"text","text":" "},{"kind":"typeIdentifier","text":"View","preciseIdentifier":"s:6TUIkit4ViewP"}],"title":"alert(_:isPresented:actions:message:borderStyle:borderColor:titleColor:)","kind":"symbol"},"doc://TUIkit/documentation/TUIkit/Spinner":{"kind":"symbol","title":"Spinner","type":"topic","navigatorTitle":[{"text":"Spinner","kind":"identifier"}],"role":"symbol","identifier":"doc:\/\/TUIkit\/documentation\/TUIkit\/Spinner","abstract":[{"text":"An animated loading indicator.","type":"text"}],"fragments":[{"text":"struct","kind":"keyword"},{"text":" ","kind":"text"},{"text":"Spinner","kind":"identifier"}],"url":"\/documentation\/tuikit\/spinner"},"doc://TUIkit/documentation/TUIkit/View/modal(content:)":{"abstract":[{"type":"text","text":"Presents this view as a modal dialog over dimmed content."}],"identifier":"doc:\/\/TUIkit\/documentation\/TUIkit\/View\/modal(content:)","type":"topic","role":"symbol","url":"\/documentation\/tuikit\/view\/modal(content:)","fragments":[{"kind":"keyword","text":"func"},{"kind":"text","text":" "},{"kind":"identifier","text":"modal"},{"kind":"text","text":"<"},{"kind":"genericParameter","text":"Modal"},{"kind":"text","text":">("},{"kind":"externalParam","text":"content"},{"kind":"text","text":": () -> "},{"kind":"typeIdentifier","text":"Modal"},{"kind":"text","text":") -> "},{"kind":"keyword","text":"some"},{"kind":"text","text":" "},{"kind":"typeIdentifier","text":"View","preciseIdentifier":"s:6TUIkit4ViewP"}],"title":"modal(content:)","kind":"symbol"},"doc://TUIkit/documentation/TUIkit/View/padding(_:)-9pnxu":{"identifier":"doc:\/\/TUIkit\/documentation\/TUIkit\/View\/padding(_:)-9pnxu","url":"\/documentation\/tuikit\/view\/padding(_:)-9pnxu","kind":"symbol","fragments":[{"kind":"keyword","text":"func"},{"kind":"text","text":" "},{"kind":"identifier","text":"padding"},{"kind":"text","text":"("},{"kind":"typeIdentifier","preciseIdentifier":"s:Si","text":"Int"},{"kind":"text","text":") -> "},{"kind":"keyword","text":"some"},{"kind":"text","text":" "},{"kind":"typeIdentifier","preciseIdentifier":"s:6TUIkit4ViewP","text":"View"}],"title":"padding(_:)","type":"topic","abstract":[{"type":"text","text":"Adds padding on all sides."}],"role":"symbol"},"doc://TUIkit/documentation/TUIkit/FrameBuffer":{"abstract":[{"type":"text","text":"A 2D text buffer that views render into before flushing to the terminal."}],"navigatorTitle":[{"kind":"identifier","text":"FrameBuffer"}],"title":"FrameBuffer","type":"topic","kind":"symbol","identifier":"doc:\/\/TUIkit\/documentation\/TUIkit\/FrameBuffer","url":"\/documentation\/tuikit\/framebuffer","role":"symbol","fragments":[{"kind":"keyword","text":"struct"},{"kind":"text","text":" "},{"kind":"identifier","text":"FrameBuffer"}]},"doc://TUIkit/documentation/TUIkit/Swift/Never":{"identifier":"doc:\/\/TUIkit\/documentation\/TUIkit\/Swift\/Never","fragments":[{"text":"extension","kind":"keyword"},{"text":" ","kind":"text"},{"text":"Never","kind":"identifier","preciseIdentifier":"s:s5NeverO"}],"type":"topic","kind":"symbol","title":"Never","url":"\/documentation\/tuikit\/swift\/never","navigatorTitle":[{"text":"Never","kind":"identifier"}],"abstract":[{"code":"Never","type":"codeVoice"},{"text":" conforms to View for views that have no body.","type":"text"}],"role":"symbol"},"doc://TUIkit/documentation/TUIkit/Slider":{"type":"topic","fragments":[{"text":"struct","kind":"keyword"},{"text":" ","kind":"text"},{"text":"Slider","kind":"identifier"}],"role":"symbol","navigatorTitle":[{"text":"Slider","kind":"identifier"}],"url":"\/documentation\/tuikit\/slider","kind":"symbol","identifier":"doc:\/\/TUIkit\/documentation\/TUIkit\/Slider","title":"Slider","abstract":[{"type":"text","text":"A control for selecting a value from a bounded linear range of values."}]},"doc://TUIkit/documentation/TUIkit/ListRowSeparatorModifier":{"url":"\/documentation\/tuikit\/listrowseparatormodifier","abstract":[{"text":"A stub modifier for list row separators.","type":"text"}],"navigatorTitle":[{"kind":"identifier","text":"ListRowSeparatorModifier"}],"type":"topic","title":"ListRowSeparatorModifier","identifier":"doc:\/\/TUIkit\/documentation\/TUIkit\/ListRowSeparatorModifier","fragments":[{"kind":"keyword","text":"struct"},{"kind":"text","text":" "},{"kind":"identifier","text":"ListRowSeparatorModifier"}],"role":"symbol","kind":"symbol"},"doc://TUIkit/documentation/TUIkit/View/border(_:color:)":{"url":"\/documentation\/tuikit\/view\/border(_:color:)","abstract":[{"type":"text","text":"Adds a border around this view."}],"fragments":[{"text":"func","kind":"keyword"},{"text":" ","kind":"text"},{"text":"border","kind":"identifier"},{"text":"(","kind":"text"},{"text":"BorderStyle","kind":"typeIdentifier","preciseIdentifier":"s:6TUIkit11BorderStyleV"},{"text":"?, ","kind":"text"},{"text":"color","kind":"externalParam"},{"text":": ","kind":"text"},{"text":"Color","kind":"typeIdentifier","preciseIdentifier":"s:6TUIkit5ColorV"},{"text":"?) -> ","kind":"text"},{"text":"some","kind":"keyword"},{"text":" ","kind":"text"},{"text":"View","kind":"typeIdentifier","preciseIdentifier":"s:6TUIkit4ViewP"}],"identifier":"doc:\/\/TUIkit\/documentation\/TUIkit\/View\/border(_:color:)","title":"border(_:color:)","role":"symbol","kind":"symbol","type":"topic"},"doc://TUIkit/documentation/TUIkit/View/onKeyPress(keys:handler:)":{"title":"onKeyPress(keys:handler:)","kind":"symbol","identifier":"doc:\/\/TUIkit\/documentation\/TUIkit\/View\/onKeyPress(keys:handler:)","abstract":[{"text":"Adds a handler for specific key press events.","type":"text"}],"fragments":[{"text":"func","kind":"keyword"},{"text":" ","kind":"text"},{"text":"onKeyPress","kind":"identifier"},{"text":"(","kind":"text"},{"text":"keys","kind":"externalParam"},{"text":": ","kind":"text"},{"text":"Set","preciseIdentifier":"s:Sh","kind":"typeIdentifier"},{"text":"<","kind":"text"},{"text":"Key","preciseIdentifier":"s:6TUIkit3KeyO","kind":"typeIdentifier"},{"text":">, ","kind":"text"},{"text":"handler","kind":"externalParam"},{"text":": (","kind":"text"},{"text":"KeyEvent","preciseIdentifier":"s:6TUIkit8KeyEventV","kind":"typeIdentifier"},{"text":") -> ","kind":"text"},{"text":"Bool","preciseIdentifier":"s:Sb","kind":"typeIdentifier"},{"text":") -> ","kind":"text"},{"text":"some","kind":"keyword"},{"kind":"text","text":" "},{"kind":"typeIdentifier","preciseIdentifier":"s:6TUIkit4ViewP","text":"View"}],"type":"topic","url":"\/documentation\/tuikit\/view\/onkeypress(keys:handler:)","role":"symbol"},"doc://TUIkit/documentation/TUIkit/View/alert(_:isPresented:actions:borderStyle:borderColor:titleColor:)":{"type":"topic","fragments":[{"text":"func","kind":"keyword"},{"text":" ","kind":"text"},{"text":"alert","kind":"identifier"},{"text":"<","kind":"text"},{"text":"Actions","kind":"genericParameter"},{"text":">(","kind":"text"},{"text":"String","kind":"typeIdentifier","preciseIdentifier":"s:SS"},{"text":", ","kind":"text"},{"text":"isPresented","kind":"externalParam"},{"text":": ","kind":"text"},{"text":"Binding","kind":"typeIdentifier","preciseIdentifier":"s:6TUIkit7BindingV"},{"text":"<","kind":"text"},{"text":"Bool","kind":"typeIdentifier","preciseIdentifier":"s:Sb"},{"text":">, ","kind":"text"},{"text":"actions","kind":"externalParam"},{"text":": () -> ","kind":"text"},{"text":"Actions","kind":"typeIdentifier"},{"text":", ","kind":"text"},{"text":"borderStyle","kind":"externalParam"},{"text":": ","kind":"text"},{"text":"BorderStyle","kind":"typeIdentifier","preciseIdentifier":"s:6TUIkit11BorderStyleV"},{"text":"?, ","kind":"text"},{"text":"borderColor","kind":"externalParam"},{"text":": ","kind":"text"},{"text":"Color","kind":"typeIdentifier","preciseIdentifier":"s:6TUIkit5ColorV"},{"text":"?, ","kind":"text"},{"text":"titleColor","kind":"externalParam"},{"text":": ","kind":"text"},{"text":"Color","kind":"typeIdentifier","preciseIdentifier":"s:6TUIkit5ColorV"},{"text":"?) -> ","kind":"text"},{"text":"some","kind":"keyword"},{"text":" ","kind":"text"},{"text":"View","kind":"typeIdentifier","preciseIdentifier":"s:6TUIkit4ViewP"}],"role":"symbol","kind":"symbol","abstract":[{"type":"text","text":"Presents an alert with title and actions only (no message)."}],"identifier":"doc:\/\/TUIkit\/documentation\/TUIkit\/View\/alert(_:isPresented:actions:borderStyle:borderColor:titleColor:)","title":"alert(_:isPresented:actions:borderStyle:borderColor:titleColor:)","url":"\/documentation\/tuikit\/view\/alert(_:ispresented:actions:borderstyle:bordercolor:titlecolor:)"},"doc://TUIkit/documentation/TUIkit/View/padding(_:)-6paoy":{"fragments":[{"kind":"keyword","text":"func"},{"kind":"text","text":" "},{"kind":"identifier","text":"padding"},{"kind":"text","text":"("},{"kind":"typeIdentifier","text":"EdgeInsets","preciseIdentifier":"s:6TUIkit10EdgeInsetsV"},{"kind":"text","text":") -> "},{"kind":"keyword","text":"some"},{"kind":"text","text":" "},{"kind":"typeIdentifier","text":"View","preciseIdentifier":"s:6TUIkit4ViewP"}],"type":"topic","title":"padding(_:)","role":"symbol","url":"\/documentation\/tuikit\/view\/padding(_:)-6paoy","kind":"symbol","identifier":"doc:\/\/TUIkit\/documentation\/TUIkit\/View\/padding(_:)-6paoy","abstract":[{"text":"Adds padding with explicit edge insets.","type":"text"}]},"doc://TUIkit/documentation/TUIkit/View/statusBarItems(context:items:)":{"url":"\/documentation\/tuikit\/view\/statusbaritems(context:items:)","identifier":"doc:\/\/TUIkit\/documentation\/TUIkit\/View\/statusBarItems(context:items:)","kind":"symbol","abstract":[{"text":"Sets the status bar items for this view with a named context.","type":"text"}],"role":"symbol","type":"topic","title":"statusBarItems(context:items:)","fragments":[{"kind":"keyword","text":"func"},{"kind":"text","text":" "},{"kind":"identifier","text":"statusBarItems"},{"kind":"text","text":"("},{"kind":"externalParam","text":"context"},{"kind":"text","text":": "},{"kind":"typeIdentifier","text":"String","preciseIdentifier":"s:SS"},{"kind":"text","text":", "},{"kind":"externalParam","text":"items"},{"kind":"text","text":": [any "},{"kind":"typeIdentifier","text":"StatusBarItemProtocol","preciseIdentifier":"s:6TUIkit21StatusBarItemProtocolP"},{"kind":"text","text":"]) -> "},{"kind":"keyword","text":"some"},{"kind":"text","text":" "},{"kind":"typeIdentifier","text":"View","preciseIdentifier":"s:6TUIkit4ViewP"}]},"doc://TUIkit/documentation/TUIkit/ModalPresentationModifier":{"abstract":[{"text":"A modifier that presents content as a centered modal overlay when a binding is true.","type":"text"}],"url":"\/documentation\/tuikit\/modalpresentationmodifier","kind":"symbol","type":"topic","title":"ModalPresentationModifier","navigatorTitle":[{"kind":"identifier","text":"ModalPresentationModifier"}],"role":"symbol","fragments":[{"kind":"keyword","text":"struct"},{"kind":"text","text":" "},{"kind":"identifier","text":"ModalPresentationModifier"}],"identifier":"doc:\/\/TUIkit\/documentation\/TUIkit\/ModalPresentationModifier"},"doc://TUIkit/documentation/TUIkit/View/task(priority:_:)":{"kind":"symbol","url":"\/documentation\/tuikit\/view\/task(priority:_:)","abstract":[{"text":"Starts an async task when this view appears.","type":"text"}],"role":"symbol","identifier":"doc:\/\/TUIkit\/documentation\/TUIkit\/View\/task(priority:_:)","fragments":[{"kind":"keyword","text":"func"},{"kind":"text","text":" "},{"kind":"identifier","text":"task"},{"kind":"text","text":"("},{"kind":"externalParam","text":"priority"},{"kind":"text","text":": "},{"preciseIdentifier":"s:ScP","kind":"typeIdentifier","text":"TaskPriority"},{"kind":"text","text":", () "},{"kind":"keyword","text":"async"},{"kind":"text","text":" -> "},{"preciseIdentifier":"s:s4Voida","kind":"typeIdentifier","text":"Void"},{"kind":"text","text":") -> "},{"kind":"keyword","text":"some"},{"kind":"text","text":" "},{"preciseIdentifier":"s:6TUIkit4ViewP","kind":"typeIdentifier","text":"View"}],"type":"topic","title":"task(priority:_:)"},"doc://TUIkit/documentation/TUIkit/EquatableView":{"url":"\/documentation\/tuikit\/equatableview","kind":"symbol","type":"topic","title":"EquatableView","navigatorTitle":[{"kind":"identifier","text":"EquatableView"}],"role":"symbol","fragments":[{"kind":"keyword","text":"struct"},{"kind":"text","text":" "},{"kind":"identifier","text":"EquatableView"}],"abstract":[{"type":"text","text":"A wrapper that enables subtree memoization for views conforming to "},{"type":"codeVoice","code":"Equatable"},{"type":"text","text":"."}],"identifier":"doc:\/\/TUIkit\/documentation\/TUIkit\/EquatableView"},"doc://TUIkit/documentation/TUIkit/View/statusBarItems(_:)-1sycu":{"url":"\/documentation\/tuikit\/view\/statusbaritems(_:)-1sycu","identifier":"doc:\/\/TUIkit\/documentation\/TUIkit\/View\/statusBarItems(_:)-1sycu","kind":"symbol","abstract":[{"text":"Sets the status bar items for this view.","type":"text"}],"role":"symbol","type":"topic","title":"statusBarItems(_:)","fragments":[{"kind":"keyword","text":"func"},{"kind":"text","text":" "},{"kind":"identifier","text":"statusBarItems"},{"kind":"text","text":"([any "},{"kind":"typeIdentifier","text":"StatusBarItemProtocol","preciseIdentifier":"s:6TUIkit21StatusBarItemProtocolP"},{"kind":"text","text":"]) -> "},{"kind":"keyword","text":"some"},{"kind":"text","text":" "},{"kind":"typeIdentifier","text":"View","preciseIdentifier":"s:6TUIkit4ViewP"}]},"doc://TUIkit/documentation/TUIkit/ProgressView":{"url":"\/documentation\/tuikit\/progressview","abstract":[{"type":"text","text":"A view that shows the progress toward completion of a task."}],"fragments":[{"kind":"keyword","text":"struct"},{"kind":"text","text":" "},{"kind":"identifier","text":"ProgressView"}],"role":"symbol","identifier":"doc:\/\/TUIkit\/documentation\/TUIkit\/ProgressView","kind":"symbol","title":"ProgressView","type":"topic","navigatorTitle":[{"kind":"identifier","text":"ProgressView"}]},"doc://TUIkit/documentation/TUIkit/View/badge(_:)-6or8s":{"fragments":[{"kind":"keyword","text":"func"},{"kind":"text","text":" "},{"kind":"identifier","text":"badge"},{"kind":"text","text":"("},{"kind":"typeIdentifier","text":"Int","preciseIdentifier":"s:Si"},{"kind":"text","text":") -> "},{"kind":"keyword","text":"some"},{"kind":"text","text":" "},{"kind":"typeIdentifier","text":"View","preciseIdentifier":"s:6TUIkit4ViewP"}],"type":"topic","title":"badge(_:)","role":"symbol","url":"\/documentation\/tuikit\/view\/badge(_:)-6or8s","kind":"symbol","identifier":"doc:\/\/TUIkit\/documentation\/TUIkit\/View\/badge(_:)-6or8s","abstract":[{"text":"Adds a badge to the view displaying a count.","type":"text"}]},"doc://TUIkit/documentation/TUIkit/FlexibleFrameView":{"role":"symbol","type":"topic","navigatorTitle":[{"text":"FlexibleFrameView","kind":"identifier"}],"title":"FlexibleFrameView","abstract":[{"type":"text","text":"A view that applies flexible frame constraints to its content."}],"url":"\/documentation\/tuikit\/flexibleframeview","fragments":[{"text":"struct","kind":"keyword"},{"text":" ","kind":"text"},{"text":"FlexibleFrameView","kind":"identifier"}],"identifier":"doc:\/\/TUIkit\/documentation\/TUIkit\/FlexibleFrameView","kind":"symbol"},"doc://TUIkit/documentation/TUIkit/Swift/Optional":{"conformance":{"conformancePrefix":[{"type":"text","text":"Conforms when"}],"availabilityPrefix":[{"type":"text","text":"Available when"}],"constraints":[{"type":"codeVoice","code":"Wrapped"},{"type":"text","text":" conforms to "},{"type":"codeVoice","code":"View"},{"type":"text","text":"."}]},"fragments":[{"kind":"keyword","text":"extension"},{"kind":"text","text":" "},{"kind":"identifier","text":"Optional","preciseIdentifier":"s:Sq"}],"role":"symbol","navigatorTitle":[{"kind":"identifier","text":"Optional"}],"identifier":"doc:\/\/TUIkit\/documentation\/TUIkit\/Swift\/Optional","kind":"symbol","abstract":[{"text":"Optional views conform to View when their Wrapped type does.","type":"text"}],"type":"topic","url":"\/documentation\/tuikit\/swift\/optional","title":"Optional"},"doc://TUIkit/documentation/TUIkit/View/onDisappear(perform:)":{"fragments":[{"kind":"keyword","text":"func"},{"kind":"text","text":" "},{"kind":"identifier","text":"onDisappear"},{"kind":"text","text":"("},{"kind":"externalParam","text":"perform"},{"kind":"text","text":": () -> "},{"kind":"typeIdentifier","text":"Void","preciseIdentifier":"s:s4Voida"},{"kind":"text","text":") -> "},{"kind":"keyword","text":"some"},{"kind":"text","text":" "},{"kind":"typeIdentifier","text":"View","preciseIdentifier":"s:6TUIkit4ViewP"}],"type":"topic","title":"onDisappear(perform:)","role":"symbol","url":"\/documentation\/tuikit\/view\/ondisappear(perform:)","kind":"symbol","identifier":"doc:\/\/TUIkit\/documentation\/TUIkit\/View\/onDisappear(perform:)","abstract":[{"text":"Executes an action when this view disappears.","type":"text"}]},"doc://TUIkit/documentation/TUIkit/Divider":{"navigatorTitle":[{"kind":"identifier","text":"Divider"}],"url":"\/documentation\/tuikit\/divider","abstract":[{"type":"text","text":"A visual separator between views."}],"title":"Divider","role":"symbol","fragments":[{"kind":"keyword","text":"struct"},{"kind":"text","text":" "},{"kind":"identifier","text":"Divider"}],"type":"topic","kind":"symbol","identifier":"doc:\/\/TUIkit\/documentation\/TUIkit\/Divider"},"doc://TUIkit/documentation/TUIkit/View/listRowSeparator(_:edges:)":{"role":"symbol","fragments":[{"kind":"keyword","text":"func"},{"kind":"text","text":" "},{"kind":"identifier","text":"listRowSeparator"},{"kind":"text","text":"("},{"kind":"typeIdentifier","text":"Visibility","preciseIdentifier":"s:6TUIkit10VisibilityO"},{"kind":"text","text":", "},{"kind":"externalParam","text":"edges"},{"kind":"text","text":": "},{"kind":"typeIdentifier","text":"VerticalEdge","preciseIdentifier":"s:6TUIkit12VerticalEdgeO"},{"kind":"text","text":"."},{"kind":"typeIdentifier","text":"Set","preciseIdentifier":"s:6TUIkit12VerticalEdgeO3SetV"},{"kind":"text","text":") -> "},{"kind":"keyword","text":"some"},{"kind":"text","text":" "},{"kind":"typeIdentifier","text":"View","preciseIdentifier":"s:6TUIkit4ViewP"}],"abstract":[{"text":"Sets the visibility of row separators within a list.","type":"text"}],"type":"topic","title":"listRowSeparator(_:edges:)","url":"\/documentation\/tuikit\/view\/listrowseparator(_:edges:)","kind":"symbol","identifier":"doc:\/\/TUIkit\/documentation\/TUIkit\/View\/listRowSeparator(_:edges:)"},"doc://TUIkit/documentation/TUIkit/View/toggleStyle(_:)":{"identifier":"doc:\/\/TUIkit\/documentation\/TUIkit\/View\/toggleStyle(_:)","kind":"symbol","abstract":[{"type":"text","text":"Sets the style for toggles within this view."}],"type":"topic","url":"\/documentation\/tuikit\/view\/togglestyle(_:)","role":"symbol","title":"toggleStyle(_:)","fragments":[{"text":"func","kind":"keyword"},{"text":" ","kind":"text"},{"text":"toggleStyle","kind":"identifier"},{"text":"<","kind":"text"},{"text":"S","kind":"genericParameter"},{"text":">(","kind":"text"},{"text":"S","kind":"typeIdentifier"},{"text":") -> ","kind":"text"},{"text":"some","kind":"keyword"},{"text":" ","kind":"text"},{"text":"View","kind":"typeIdentifier","preciseIdentifier":"s:6TUIkit4ViewP"}]},"doc://TUIkit/documentation/TUIkit/AnyView":{"type":"topic","title":"AnyView","kind":"symbol","role":"symbol","abstract":[{"type":"text","text":"A type-erased view for conditional returns."}],"identifier":"doc:\/\/TUIkit\/documentation\/TUIkit\/AnyView","fragments":[{"text":"struct","kind":"keyword"},{"text":" ","kind":"text"},{"text":"AnyView","kind":"identifier"}],"url":"\/documentation\/tuikit\/anyview","navigatorTitle":[{"text":"AnyView","kind":"identifier"}]},"doc://TUIkit/documentation/TUIkit/KeyPressModifier":{"abstract":[{"text":"A modifier that adds a key press handler to a view.","type":"text"}],"role":"symbol","fragments":[{"text":"struct","kind":"keyword"},{"text":" ","kind":"text"},{"text":"KeyPressModifier","kind":"identifier"}],"url":"\/documentation\/tuikit\/keypressmodifier","kind":"symbol","type":"topic","navigatorTitle":[{"text":"KeyPressModifier","kind":"identifier"}],"identifier":"doc:\/\/TUIkit\/documentation\/TUIkit\/KeyPressModifier","title":"KeyPressModifier"},"doc://TUIkit/documentation/TUIkit/Alert":{"abstract":[{"text":"A modal alert view that displays a title, message, and optional action buttons.","type":"text"}],"kind":"symbol","title":"Alert","role":"symbol","url":"\/documentation\/tuikit\/alert","fragments":[{"text":"struct","kind":"keyword"},{"text":" ","kind":"text"},{"text":"Alert","kind":"identifier"}],"type":"topic","navigatorTitle":[{"text":"Alert","kind":"identifier"}],"identifier":"doc:\/\/TUIkit\/documentation\/TUIkit\/Alert"},"doc://TUIkit/documentation/TUIkit/SelectionDisabledModifier":{"url":"\/documentation\/tuikit\/selectiondisabledmodifier","navigatorTitle":[{"kind":"identifier","text":"SelectionDisabledModifier"}],"title":"SelectionDisabledModifier","kind":"symbol","role":"symbol","identifier":"doc:\/\/TUIkit\/documentation\/TUIkit\/SelectionDisabledModifier","type":"topic","abstract":[{"type":"text","text":"A modifier that disables selection for a view within a List."}],"fragments":[{"kind":"keyword","text":"struct"},{"kind":"text","text":" "},{"kind":"identifier","text":"SelectionDisabledModifier"}]},"doc://TUIkit/documentation/TUIkit/View/badge(_:)-9qomv":{"role":"symbol","fragments":[{"kind":"keyword","text":"func"},{"kind":"text","text":" "},{"kind":"identifier","text":"badge"},{"kind":"text","text":"<"},{"kind":"genericParameter","text":"S"},{"kind":"text","text":">("},{"kind":"typeIdentifier","text":"S"},{"kind":"text","text":"?) -> "},{"kind":"keyword","text":"some"},{"kind":"text","text":" "},{"kind":"typeIdentifier","text":"View","preciseIdentifier":"s:6TUIkit4ViewP"}],"abstract":[{"text":"Adds a badge to the view with a string label.","type":"text"}],"type":"topic","title":"badge(_:)","url":"\/documentation\/tuikit\/view\/badge(_:)-9qomv","kind":"symbol","identifier":"doc:\/\/TUIkit\/documentation\/TUIkit\/View\/badge(_:)-9qomv"},"doc://TUIkit/documentation/TUIkit/Table":{"identifier":"doc:\/\/TUIkit\/documentation\/TUIkit\/Table","title":"Table","abstract":[{"text":"A scrollable table with columns, keyboard navigation, and selection.","type":"text"}],"type":"topic","kind":"symbol","role":"symbol","fragments":[{"text":"struct","kind":"keyword"},{"text":" ","kind":"text"},{"text":"Table","kind":"identifier"}],"url":"\/documentation\/tuikit\/table","navigatorTitle":[{"text":"Table","kind":"identifier"}]},"doc://TUIkit/documentation/TUIkit/View/appearance(_:)":{"identifier":"doc:\/\/TUIkit\/documentation\/TUIkit\/View\/appearance(_:)","abstract":[{"text":"Sets the appearance for this view and its descendants.","type":"text"}],"title":"appearance(_:)","url":"\/documentation\/tuikit\/view\/appearance(_:)","role":"symbol","type":"topic","fragments":[{"kind":"keyword","text":"func"},{"kind":"text","text":" "},{"kind":"identifier","text":"appearance"},{"kind":"text","text":"("},{"kind":"typeIdentifier","text":"Appearance","preciseIdentifier":"s:6TUIkit10AppearanceV"},{"kind":"text","text":") -> "},{"kind":"keyword","text":"some"},{"kind":"text","text":" "},{"kind":"typeIdentifier","text":"View","preciseIdentifier":"s:6TUIkit4ViewP"}],"kind":"symbol"},"doc://TUIkit/documentation/TUIkit/View/body-swift.property":{"identifier":"doc:\/\/TUIkit\/documentation\/TUIkit\/View\/body-swift.property","abstract":[{"text":"The content and behavior of this view.","type":"text"}],"title":"body","type":"topic","role":"symbol","required":true,"fragments":[{"kind":"keyword","text":"var"},{"kind":"text","text":" "},{"kind":"identifier","text":"body"},{"kind":"text","text":": "},{"kind":"typeIdentifier","text":"Self"},{"kind":"text","text":"."},{"kind":"typeIdentifier","text":"Body","preciseIdentifier":"s:6TUIkit4ViewP4BodyQa"}],"url":"\/documentation\/tuikit\/view\/body-swift.property","kind":"symbol"},"doc://TUIkit/documentation/TUIkit/View/environment(_:_:)":{"type":"topic","kind":"symbol","url":"\/documentation\/tuikit\/view\/environment(_:_:)","title":"environment(_:_:)","role":"symbol","identifier":"doc:\/\/TUIkit\/documentation\/TUIkit\/View\/environment(_:_:)","fragments":[{"kind":"keyword","text":"func"},{"kind":"text","text":" "},{"kind":"identifier","text":"environment"},{"kind":"text","text":"<"},{"kind":"genericParameter","text":"V"},{"kind":"text","text":">("},{"kind":"typeIdentifier","text":"WritableKeyPath","preciseIdentifier":"s:s15WritableKeyPathC"},{"kind":"text","text":"<"},{"kind":"typeIdentifier","text":"EnvironmentValues","preciseIdentifier":"s:6TUIkit17EnvironmentValuesV"},{"kind":"text","text":", "},{"kind":"typeIdentifier","text":"V"},{"kind":"text","text":">, "},{"kind":"typeIdentifier","text":"V"},{"kind":"text","text":") -> "},{"kind":"keyword","text":"some"},{"kind":"text","text":" "},{"kind":"typeIdentifier","text":"View","preciseIdentifier":"s:6TUIkit4ViewP"}],"abstract":[{"text":"Sets an environment value for this view and its children.","type":"text"}]},"doc://TUIkit/documentation/TUIkit/View/statusBarItems(_:)-9hfph":{"type":"topic","kind":"symbol","url":"\/documentation\/tuikit\/view\/statusbaritems(_:)-9hfph","title":"statusBarItems(_:)","role":"symbol","identifier":"doc:\/\/TUIkit\/documentation\/TUIkit\/View\/statusBarItems(_:)-9hfph","fragments":[{"kind":"keyword","text":"func"},{"kind":"text","text":" "},{"kind":"identifier","text":"statusBarItems"},{"kind":"text","text":"(() -> [any "},{"kind":"typeIdentifier","text":"StatusBarItemProtocol","preciseIdentifier":"s:6TUIkit21StatusBarItemProtocolP"},{"kind":"text","text":"]) -> "},{"kind":"keyword","text":"some"},{"kind":"text","text":" "},{"kind":"typeIdentifier","text":"View","preciseIdentifier":"s:6TUIkit4ViewP"}],"abstract":[{"text":"Declares status bar items for this view using a builder.","type":"text"}]},"doc://TUIkit/documentation/TUIkit/View/onKeyPress(_:)":{"role":"symbol","kind":"symbol","type":"topic","abstract":[{"text":"Adds a handler for key press events.","type":"text"}],"title":"onKeyPress(_:)","fragments":[{"kind":"keyword","text":"func"},{"kind":"text","text":" "},{"kind":"identifier","text":"onKeyPress"},{"kind":"text","text":"(("},{"kind":"typeIdentifier","text":"KeyEvent","preciseIdentifier":"s:6TUIkit8KeyEventV"},{"kind":"text","text":") -> "},{"kind":"typeIdentifier","text":"Bool","preciseIdentifier":"s:Sb"},{"kind":"text","text":") -> "},{"kind":"keyword","text":"some"},{"kind":"text","text":" "},{"kind":"typeIdentifier","text":"View","preciseIdentifier":"s:6TUIkit4ViewP"}],"identifier":"doc:\/\/TUIkit\/documentation\/TUIkit\/View\/onKeyPress(_:)","url":"\/documentation\/tuikit\/view\/onkeypress(_:)"},"doc://TUIkit/documentation/TUIkit/TupleView":{"role":"symbol","identifier":"doc:\/\/TUIkit\/documentation\/TUIkit\/TupleView","url":"\/documentation\/tuikit\/tupleview","abstract":[{"type":"text","text":"A view that contains multiple child views packed via a parameter pack."}],"title":"TupleView","fragments":[{"text":"struct","kind":"keyword"},{"text":" ","kind":"text"},{"text":"TupleView","kind":"identifier"}],"kind":"symbol","navigatorTitle":[{"text":"TupleView","kind":"identifier"}],"type":"topic"},"doc://TUIkit/documentation/TUIkit/RadioButtonGroup":{"abstract":[{"type":"text","text":"An interactive radio button group for single-selection from multiple options."}],"type":"topic","url":"\/documentation\/tuikit\/radiobuttongroup","kind":"symbol","title":"RadioButtonGroup","identifier":"doc:\/\/TUIkit\/documentation\/TUIkit\/RadioButtonGroup","navigatorTitle":[{"text":"RadioButtonGroup","kind":"identifier"}],"fragments":[{"text":"struct","kind":"keyword"},{"text":" ","kind":"text"},{"text":"RadioButtonGroup","kind":"identifier"}],"role":"symbol"},"doc://TUIkit/documentation/TUIkit/View/navigationSplitViewColumnWidth(min:ideal:max:)":{"title":"navigationSplitViewColumnWidth(min:ideal:max:)","type":"topic","role":"symbol","fragments":[{"kind":"keyword","text":"func"},{"kind":"text","text":" "},{"kind":"identifier","text":"navigationSplitViewColumnWidth"},{"kind":"text","text":"("},{"kind":"externalParam","text":"min"},{"kind":"text","text":": "},{"kind":"typeIdentifier","text":"Int","preciseIdentifier":"s:Si"},{"kind":"text","text":"?, "},{"kind":"externalParam","text":"ideal"},{"kind":"text","text":": "},{"kind":"typeIdentifier","text":"Int","preciseIdentifier":"s:Si"},{"kind":"text","text":"?, "},{"kind":"externalParam","text":"max"},{"kind":"text","text":": "},{"kind":"typeIdentifier","text":"Int","preciseIdentifier":"s:Si"},{"kind":"text","text":"?) -> "},{"kind":"keyword","text":"some"},{"kind":"text","text":" "},{"kind":"typeIdentifier","text":"View","preciseIdentifier":"s:6TUIkit4ViewP"}],"identifier":"doc:\/\/TUIkit\/documentation\/TUIkit\/View\/navigationSplitViewColumnWidth(min:ideal:max:)","abstract":[{"text":"Sets flexible width constraints for a navigation split view column.","type":"text"}],"url":"\/documentation\/tuikit\/view\/navigationsplitviewcolumnwidth(min:ideal:max:)","kind":"symbol"},"doc://TUIkit/documentation/TUIkit/View/navigationSplitViewStyle(_:)":{"title":"navigationSplitViewStyle(_:)","type":"topic","role":"symbol","fragments":[{"kind":"keyword","text":"func"},{"kind":"text","text":" "},{"kind":"identifier","text":"navigationSplitViewStyle"},{"kind":"text","text":"<"},{"kind":"genericParameter","text":"S"},{"kind":"text","text":">("},{"kind":"typeIdentifier","text":"S"},{"kind":"text","text":") -> "},{"kind":"keyword","text":"some"},{"kind":"text","text":" "},{"kind":"typeIdentifier","text":"View","preciseIdentifier":"s:6TUIkit4ViewP"}],"identifier":"doc:\/\/TUIkit\/documentation\/TUIkit\/View\/navigationSplitViewStyle(_:)","abstract":[{"text":"Sets the style for navigation split views within this view.","type":"text"}],"url":"\/documentation\/tuikit\/view\/navigationsplitviewstyle(_:)","kind":"symbol"},"doc://TUIkit/documentation/TUIkit/View":{"title":"View","fragments":[{"text":"protocol","kind":"keyword"},{"text":" ","kind":"text"},{"text":"View","kind":"identifier"}],"navigatorTitle":[{"text":"View","kind":"identifier"}],"type":"topic","kind":"symbol","abstract":[{"type":"text","text":"The base protocol for all TUIkit views."}],"role":"symbol","url":"\/documentation\/tuikit\/view","identifier":"doc:\/\/TUIkit\/documentation\/TUIkit\/View"},"doc://TUIkit/documentation/TUIkit/View/background(_:)":{"abstract":[{"text":"Adds a background color to this view.","type":"text"}],"title":"background(_:)","url":"\/documentation\/tuikit\/view\/background(_:)","identifier":"doc:\/\/TUIkit\/documentation\/TUIkit\/View\/background(_:)","role":"symbol","type":"topic","fragments":[{"kind":"keyword","text":"func"},{"kind":"text","text":" "},{"kind":"identifier","text":"background"},{"kind":"text","text":"("},{"kind":"typeIdentifier","text":"Color","preciseIdentifier":"s:6TUIkit5ColorV"},{"kind":"text","text":") -> "},{"kind":"keyword","text":"some"},{"kind":"text","text":" "},{"kind":"typeIdentifier","text":"View","preciseIdentifier":"s:6TUIkit4ViewP"}],"kind":"symbol"},"doc://TUIkit/documentation/TUIkit/HStack":{"navigatorTitle":[{"text":"HStack","kind":"identifier"}],"abstract":[{"text":"A view that arranges its children horizontally.","type":"text"}],"fragments":[{"text":"struct","kind":"keyword"},{"text":" ","kind":"text"},{"text":"HStack","kind":"identifier"}],"kind":"symbol","title":"HStack","identifier":"doc:\/\/TUIkit\/documentation\/TUIkit\/HStack","role":"symbol","type":"topic","url":"\/documentation\/tuikit\/hstack"},"doc://TUIkit/documentation/TUIkit/View/navigationTitle(_:)":{"fragments":[{"kind":"keyword","text":"func"},{"kind":"text","text":" "},{"kind":"identifier","text":"navigationTitle"},{"kind":"text","text":"("},{"kind":"typeIdentifier","text":"String","preciseIdentifier":"s:SS"},{"kind":"text","text":") -> "},{"kind":"keyword","text":"some"},{"kind":"text","text":" "},{"kind":"typeIdentifier","text":"View","preciseIdentifier":"s:6TUIkit4ViewP"}],"kind":"symbol","type":"topic","title":"navigationTitle(_:)","role":"symbol","url":"\/documentation\/tuikit\/view\/navigationtitle(_:)","identifier":"doc:\/\/TUIkit\/documentation\/TUIkit\/View\/navigationTitle(_:)","abstract":[{"text":"Sets the navigation title for this view.","type":"text"}]},"doc://TUIkit/documentation/TUIkit/View/overlay(alignment:content:)":{"type":"topic","kind":"symbol","abstract":[{"text":"Layers the specified view on top of this view.","type":"text"}],"url":"\/documentation\/tuikit\/view\/overlay(alignment:content:)","identifier":"doc:\/\/TUIkit\/documentation\/TUIkit\/View\/overlay(alignment:content:)","title":"overlay(alignment:content:)","role":"symbol","fragments":[{"kind":"keyword","text":"func"},{"kind":"text","text":" "},{"kind":"identifier","text":"overlay"},{"kind":"text","text":"<"},{"kind":"genericParameter","text":"Overlay"},{"kind":"text","text":">("},{"kind":"externalParam","text":"alignment"},{"kind":"text","text":": "},{"kind":"typeIdentifier","text":"Alignment","preciseIdentifier":"s:6TUIkit9AlignmentV"},{"kind":"text","text":", "},{"kind":"externalParam","text":"content"},{"kind":"text","text":": () -> "},{"kind":"typeIdentifier","text":"Overlay"},{"kind":"text","text":") -> "},{"kind":"keyword","text":"some"},{"kind":"text","text":" "},{"kind":"typeIdentifier","text":"View","preciseIdentifier":"s:6TUIkit4ViewP"}]},"doc://TUIkit/documentation/TUIkit/AlertPresentationModifier":{"kind":"symbol","abstract":[{"type":"text","text":"A modifier that presents an alert dialog when a binding is true."}],"type":"topic","url":"\/documentation\/tuikit\/alertpresentationmodifier","role":"symbol","identifier":"doc:\/\/TUIkit\/documentation\/TUIkit\/AlertPresentationModifier","navigatorTitle":[{"kind":"identifier","text":"AlertPresentationModifier"}],"title":"AlertPresentationModifier","fragments":[{"kind":"keyword","text":"struct"},{"kind":"text","text":" "},{"kind":"identifier","text":"AlertPresentationModifier"}]},"doc://TUIkit/documentation/TUIkit/ConditionalView":{"role":"symbol","type":"topic","navigatorTitle":[{"text":"ConditionalView","kind":"identifier"}],"title":"ConditionalView","abstract":[{"text":"A view that represents either the true or false branch of a conditional.","type":"text"}],"url":"\/documentation\/tuikit\/conditionalview","fragments":[{"text":"enum","kind":"keyword"},{"text":" ","kind":"text"},{"text":"ConditionalView","kind":"identifier"}],"identifier":"doc:\/\/TUIkit\/documentation\/TUIkit\/ConditionalView","kind":"symbol"},"doc://TUIkit/documentation/TUIkit/View/asAnyView()":{"type":"topic","kind":"symbol","abstract":[{"text":"Wraps this view in an AnyView for type erasure.","type":"text"}],"url":"\/documentation\/tuikit\/view\/asanyview()","identifier":"doc:\/\/TUIkit\/documentation\/TUIkit\/View\/asAnyView()","title":"asAnyView()","role":"symbol","fragments":[{"kind":"keyword","text":"func"},{"kind":"text","text":" "},{"kind":"identifier","text":"asAnyView"},{"kind":"text","text":"() -> "},{"kind":"typeIdentifier","text":"AnyView","preciseIdentifier":"s:6TUIkit7AnyViewV"}]},"doc://TUIkit/documentation/TUIkit/View/navigationSplitViewColumnWidth(_:)":{"url":"\/documentation\/tuikit\/view\/navigationsplitviewcolumnwidth(_:)","fragments":[{"kind":"keyword","text":"func"},{"kind":"text","text":" "},{"kind":"identifier","text":"navigationSplitViewColumnWidth"},{"kind":"text","text":"("},{"kind":"typeIdentifier","text":"Int","preciseIdentifier":"s:Si"},{"kind":"text","text":") -> "},{"kind":"keyword","text":"some"},{"kind":"text","text":" "},{"kind":"typeIdentifier","text":"View","preciseIdentifier":"s:6TUIkit4ViewP"}],"role":"symbol","abstract":[{"text":"Sets the preferred width for a navigation split view column.","type":"text"}],"kind":"symbol","title":"navigationSplitViewColumnWidth(_:)","type":"topic","identifier":"doc:\/\/TUIkit\/documentation\/TUIkit\/View\/navigationSplitViewColumnWidth(_:)"},"doc://TUIkit/documentation/TUIkit/View/appHeader(content:)":{"identifier":"doc:\/\/TUIkit\/documentation\/TUIkit\/View\/appHeader(content:)","kind":"symbol","abstract":[{"text":"Declares the app header content for this view.","type":"text"}],"url":"\/documentation\/tuikit\/view\/appheader(content:)","fragments":[{"kind":"keyword","text":"func"},{"kind":"text","text":" "},{"kind":"identifier","text":"appHeader"},{"kind":"text","text":"<"},{"kind":"genericParameter","text":"Header"},{"kind":"text","text":">("},{"kind":"externalParam","text":"content"},{"kind":"text","text":": () -> "},{"kind":"typeIdentifier","text":"Header"},{"kind":"text","text":") -> "},{"kind":"keyword","text":"some"},{"kind":"text","text":" "},{"kind":"typeIdentifier","text":"View","preciseIdentifier":"s:6TUIkit4ViewP"}],"title":"appHeader(content:)","type":"topic","role":"symbol"},"doc://TUIkit/documentation/TUIkit/EmptyView":{"role":"symbol","abstract":[{"type":"text","text":"A view that displays no content."}],"navigatorTitle":[{"text":"EmptyView","kind":"identifier"}],"identifier":"doc:\/\/TUIkit\/documentation\/TUIkit\/EmptyView","fragments":[{"text":"struct","kind":"keyword"},{"text":" ","kind":"text"},{"text":"EmptyView","kind":"identifier"}],"url":"\/documentation\/tuikit\/emptyview","kind":"symbol","type":"topic","title":"EmptyView"},"doc://TUIkit/documentation/TUIkit/ForEach":{"fragments":[{"text":"struct","kind":"keyword"},{"text":" ","kind":"text"},{"text":"ForEach","kind":"identifier"}],"navigatorTitle":[{"text":"ForEach","kind":"identifier"}],"url":"\/documentation\/tuikit\/foreach","identifier":"doc:\/\/TUIkit\/documentation\/TUIkit\/ForEach","abstract":[{"text":"A view that generates views from a collection of data.","type":"text"}],"kind":"symbol","title":"ForEach","type":"topic","role":"symbol"},"doc://TUIkit/documentation/TUIkit/StatusBar":{"title":"StatusBar","url":"\/documentation\/tuikit\/statusbar","role":"symbol","identifier":"doc:\/\/TUIkit\/documentation\/TUIkit\/StatusBar","kind":"symbol","abstract":[{"type":"text","text":"A status bar that displays at the bottom of the terminal."}],"type":"topic","fragments":[{"text":"struct","kind":"keyword"},{"text":" ","kind":"text"},{"text":"StatusBar","kind":"identifier"}],"navigatorTitle":[{"text":"StatusBar","kind":"identifier"}]},"doc://TUIkit/documentation/TUIkit/DimmedModifier":{"fragments":[{"kind":"keyword","text":"struct"},{"kind":"text","text":" "},{"kind":"identifier","text":"DimmedModifier"}],"title":"DimmedModifier","kind":"symbol","role":"symbol","url":"\/documentation\/tuikit\/dimmedmodifier","navigatorTitle":[{"kind":"identifier","text":"DimmedModifier"}],"type":"topic","abstract":[{"type":"text","text":"A modifier that strips all styling from content and replaces it with"},{"type":"text","text":" "},{"type":"text","text":"a uniform dimmed appearance using only two colors."}],"identifier":"doc:\/\/TUIkit\/documentation\/TUIkit\/DimmedModifier"},"doc://TUIkit/documentation/TUIkit/ViewArray":{"role":"symbol","title":"ViewArray","url":"\/documentation\/tuikit\/viewarray","abstract":[{"type":"text","text":"A view that contains an array of identical views."}],"identifier":"doc:\/\/TUIkit\/documentation\/TUIkit\/ViewArray","kind":"symbol","fragments":[{"text":"struct","kind":"keyword"},{"text":" ","kind":"text"},{"text":"ViewArray","kind":"identifier"}],"navigatorTitle":[{"text":"ViewArray","kind":"identifier"}],"type":"topic"},"doc://TUIkit/documentation/TUIkit/LazyVStack":{"navigatorTitle":[{"kind":"identifier","text":"LazyVStack"}],"identifier":"doc:\/\/TUIkit\/documentation\/TUIkit\/LazyVStack","url":"\/documentation\/tuikit\/lazyvstack","fragments":[{"kind":"keyword","text":"struct"},{"kind":"text","text":" "},{"kind":"identifier","text":"LazyVStack"}],"role":"symbol","type":"topic","kind":"symbol","abstract":[{"type":"text","text":"A view that arranges its children in a line that grows vertically,"},{"type":"text","text":" "},{"type":"text","text":"creating items only as needed."}],"title":"LazyVStack"},"doc://TUIkit/documentation/TUIkit/View/onKeyPress(_:action:)":{"abstract":[{"text":"Adds a handler for a single key press.","type":"text"}],"identifier":"doc:\/\/TUIkit\/documentation\/TUIkit\/View\/onKeyPress(_:action:)","title":"onKeyPress(_:action:)","kind":"symbol","url":"\/documentation\/tuikit\/view\/onkeypress(_:action:)","type":"topic","fragments":[{"kind":"keyword","text":"func"},{"kind":"text","text":" "},{"kind":"identifier","text":"onKeyPress"},{"kind":"text","text":"("},{"kind":"typeIdentifier","text":"Key","preciseIdentifier":"s:6TUIkit3KeyO"},{"kind":"text","text":", "},{"kind":"externalParam","text":"action"},{"kind":"text","text":": () -> "},{"kind":"typeIdentifier","text":"Void","preciseIdentifier":"s:s4Voida"},{"kind":"text","text":") -> "},{"kind":"keyword","text":"some"},{"kind":"text","text":" "},{"kind":"typeIdentifier","text":"View","preciseIdentifier":"s:6TUIkit4ViewP"}],"role":"symbol"},"doc://TUIkit/documentation/TUIkit/View/onAppear(perform:)":{"abstract":[{"text":"Executes an action when this view first appears.","type":"text"}],"url":"\/documentation\/tuikit\/view\/onappear(perform:)","type":"topic","kind":"symbol","title":"onAppear(perform:)","role":"symbol","identifier":"doc:\/\/TUIkit\/documentation\/TUIkit\/View\/onAppear(perform:)","fragments":[{"kind":"keyword","text":"func"},{"kind":"text","text":" "},{"kind":"identifier","text":"onAppear"},{"kind":"text","text":"("},{"kind":"externalParam","text":"perform"},{"kind":"text","text":": () -> "},{"kind":"typeIdentifier","text":"Void","preciseIdentifier":"s:s4Voida"},{"kind":"text","text":") -> "},{"kind":"keyword","text":"some"},{"kind":"text","text":" "},{"kind":"typeIdentifier","text":"View","preciseIdentifier":"s:6TUIkit4ViewP"}]},"doc://TUIkit/documentation/TUIkit/View/modal(isPresented:content:)":{"abstract":[{"text":"Presents a modal overlay when a binding to a Boolean value is true.","type":"text"}],"url":"\/documentation\/tuikit\/view\/modal(ispresented:content:)","type":"topic","kind":"symbol","title":"modal(isPresented:content:)","role":"symbol","identifier":"doc:\/\/TUIkit\/documentation\/TUIkit\/View\/modal(isPresented:content:)","fragments":[{"kind":"keyword","text":"func"},{"kind":"text","text":" "},{"kind":"identifier","text":"modal"},{"kind":"text","text":"<"},{"kind":"genericParameter","text":"Modal"},{"kind":"text","text":">("},{"kind":"externalParam","text":"isPresented"},{"kind":"text","text":": "},{"kind":"typeIdentifier","text":"Binding","preciseIdentifier":"s:6TUIkit7BindingV"},{"kind":"text","text":"<"},{"kind":"typeIdentifier","text":"Bool","preciseIdentifier":"s:Sb"},{"kind":"text","text":">, "},{"kind":"externalParam","text":"content"},{"kind":"text","text":": () -> "},{"kind":"typeIdentifier","text":"Modal"},{"kind":"text","text":") -> "},{"kind":"keyword","text":"some"},{"kind":"text","text":" "},{"kind":"typeIdentifier","text":"View","preciseIdentifier":"s:6TUIkit4ViewP"}]},"doc://TUIkit/documentation/TUIkit/Text":{"type":"topic","kind":"symbol","role":"symbol","fragments":[{"kind":"keyword","text":"struct"},{"kind":"text","text":" "},{"kind":"identifier","text":"Text"}],"identifier":"doc:\/\/TUIkit\/documentation\/TUIkit\/Text","title":"Text","abstract":[{"text":"A view that displays text in the terminal.","type":"text"}],"navigatorTitle":[{"kind":"identifier","text":"Text"}],"url":"\/documentation\/tuikit\/text"},"doc://TUIkit/documentation/TUIkit/View/Body-swift.associatedtype":{"abstract":[{"text":"The type of the body view.","type":"text"}],"url":"\/documentation\/tuikit\/view\/body-swift.associatedtype","type":"topic","kind":"symbol","title":"Body","required":true,"role":"symbol","identifier":"doc:\/\/TUIkit\/documentation\/TUIkit\/View\/Body-swift.associatedtype","fragments":[{"kind":"keyword","text":"associatedtype"},{"kind":"text","text":" "},{"kind":"identifier","text":"Body"},{"kind":"text","text":" : "},{"kind":"typeIdentifier","text":"View","preciseIdentifier":"s:6TUIkit4ViewP"}]},"doc://TUIkit/documentation/TUIkit/SecureField":{"kind":"symbol","role":"symbol","abstract":[{"type":"text","text":"A control for secure text entry, where the display masks the users input."}],"navigatorTitle":[{"kind":"identifier","text":"SecureField"}],"fragments":[{"kind":"keyword","text":"struct"},{"kind":"text","text":" "},{"kind":"identifier","text":"SecureField"}],"url":"\/documentation\/tuikit\/securefield","title":"SecureField","identifier":"doc:\/\/TUIkit\/documentation\/TUIkit\/SecureField","type":"topic"},"doc://TUIkit/documentation/TUIkit/VStack":{"type":"topic","title":"VStack","kind":"symbol","fragments":[{"kind":"keyword","text":"struct"},{"kind":"text","text":" "},{"kind":"identifier","text":"VStack"}],"identifier":"doc:\/\/TUIkit\/documentation\/TUIkit\/VStack","abstract":[{"text":"A view that arranges its children vertically.","type":"text"}],"navigatorTitle":[{"kind":"identifier","text":"VStack"}],"url":"\/documentation\/tuikit\/vstack","role":"symbol"},"doc://TUIkit/documentation/TUIkit/View/statusBarItems(context:_:)":{"type":"topic","url":"\/documentation\/tuikit\/view\/statusbaritems(context:_:)","title":"statusBarItems(context:_:)","identifier":"doc:\/\/TUIkit\/documentation\/TUIkit\/View\/statusBarItems(context:_:)","abstract":[{"text":"Sets the status bar items for this view with a named context.","type":"text"}],"role":"symbol","kind":"symbol","fragments":[{"text":"func","kind":"keyword"},{"text":" ","kind":"text"},{"text":"statusBarItems","kind":"identifier"},{"kind":"text","text":"("},{"kind":"externalParam","text":"context"},{"kind":"text","text":": "},{"kind":"typeIdentifier","text":"String","preciseIdentifier":"s:SS"},{"kind":"text","text":", () -> [any "},{"kind":"typeIdentifier","text":"StatusBarItemProtocol","preciseIdentifier":"s:6TUIkit21StatusBarItemProtocolP"},{"kind":"text","text":"]) -> "},{"kind":"keyword","text":"some"},{"kind":"text","text":" "},{"kind":"typeIdentifier","text":"View","preciseIdentifier":"s:6TUIkit4ViewP"}]},"doc://TUIkit/documentation/TUIkit/View/selectionDisabled(_:)":{"abstract":[{"text":"Disables selection for this view within a List.","type":"text"}],"url":"\/documentation\/tuikit\/view\/selectiondisabled(_:)","type":"topic","kind":"symbol","title":"selectionDisabled(_:)","role":"symbol","identifier":"doc:\/\/TUIkit\/documentation\/TUIkit\/View\/selectionDisabled(_:)","fragments":[{"kind":"keyword","text":"func"},{"kind":"text","text":" "},{"kind":"identifier","text":"selectionDisabled"},{"kind":"text","text":"("},{"kind":"typeIdentifier","text":"Bool","preciseIdentifier":"s:Sb"},{"kind":"text","text":") -> "},{"kind":"keyword","text":"some"},{"kind":"text","text":" "},{"kind":"typeIdentifier","text":"View","preciseIdentifier":"s:6TUIkit4ViewP"}]},"doc://TUIkit/documentation/TUIkit/Panel":{"role":"symbol","kind":"symbol","identifier":"doc:\/\/TUIkit\/documentation\/TUIkit\/Panel","title":"Panel","fragments":[{"kind":"keyword","text":"struct"},{"kind":"text","text":" "},{"kind":"identifier","text":"Panel"}],"navigatorTitle":[{"kind":"identifier","text":"Panel"}],"url":"\/documentation\/tuikit\/panel","abstract":[{"type":"text","text":"A labeled container  always has a title, optionally a footer."}],"type":"topic"},"doc://TUIkit/documentation/TUIkit/View/dimmed()":{"abstract":[{"type":"text","text":"Applies a dimming effect to the view content."}],"identifier":"doc:\/\/TUIkit\/documentation\/TUIkit\/View\/dimmed()","title":"dimmed()","url":"\/documentation\/tuikit\/view\/dimmed()","fragments":[{"text":"func","kind":"keyword"},{"text":" ","kind":"text"},{"text":"dimmed","kind":"identifier"},{"text":"() -> ","kind":"text"},{"text":"some","kind":"keyword"},{"text":" ","kind":"text"},{"text":"View","kind":"typeIdentifier","preciseIdentifier":"s:6TUIkit4ViewP"}],"kind":"symbol","role":"symbol","type":"topic"}}}